Workbook
Name ça: "$#REF !.$B$508:$R$508"
Name CA_N: [1]SIG!$B$8
Name CA_N_1: [1]SIG!$D$8
Name çb: "$#REF !.$A$48:$K$48"
Name çi: "$#REF !.$R$11:$R$508"
Name cloture: "$#REF !.$G$9"
Name çp: "$#REF !.$B$44:$F$44"
Name çr: "$#REF !.$B$62:$H$62"
Name çs: "$#REF !.$B$161:$L$161"
Name dateCloture: #REF!
Name dateCloture: #REF!
Name dateCloture: #REF!
Name dateCloture: #REF!
Name dateCloture: #REF!
Name dateCloture: #REF!
Name dateCloture: #REF!
Name dateCloture: #REF!
Name dateCloture: #REF!
Name dateCloture: #REF!
Name dateCloture: #REF!
Name dateCloture: #REF!
Name dateCloture: #REF!
Name dateCloture: #REF!
Name DatesCloture: "$#REF !.$F$9:$#REF !.$M$9"
Name Diligences: 'A100 Rappro BA-BG'!#REF!
Name Diligences: 'A110 Revue frs débiteurs'!#REF!
Name Diligences: 'A200 DPO Frs'!#REF!
Name Diligences: 'A300 Réciprocité intragroupe'!#REF!
Name Diligences: 'A410 Revue FNP'!#REF!
Name Diligences: 'A420 Revue AAR'!#REF!
Name Diligences: 'A430 Revue RFA'!#REF!
Name Diligences: 'A440 Revue CCA'!#REF!
Name Diligences: 'A450 Test cut off achats'!#REF!
Name Diligences: 'A500 Circularisations'!#REF!
Name Diligences: 'A600 Revue AACE'!#REF!
Name Diligences: 'A700 Revue EAP'!#REF!
Name Diligences: 'A800 Frs en devise'!#REF!
Name Diligences: #REF!
Name Etat: 'A100 Rappro BA-BG'!#REF!
Name Etat: 'A110 Revue frs débiteurs'!#REF!
Name Etat: 'A200 DPO Frs'!#REF!
Name Etat: 'A300 Réciprocité intragroupe'!#REF!
Name Etat: 'A410 Revue FNP'!#REF!
Name Etat: 'A420 Revue AAR'!#REF!
Name Etat: 'A430 Revue RFA'!#REF!
Name Etat: 'A440 Revue CCA'!#REF!
Name Etat: 'A450 Test cut off achats'!#REF!
Name Etat: 'A500 Circularisations'!#REF!
Name Etat: 'A600 Revue AACE'!#REF!
Name Etat: 'A700 Revue EAP'!#REF!
Name Etat: 'A800 Frs en devise'!#REF!
Name Etat: #REF!
Name NomDossier: "$#REF !.$E$1"
Name RAS: 'A100 Rappro BA-BG'!#REF!
Name RAS: 'A110 Revue frs débiteurs'!#REF!
Name RAS: 'A200 DPO Frs'!#REF!
Name RAS: 'A300 Réciprocité intragroupe'!#REF!
Name RAS: 'A410 Revue FNP'!#REF!
Name RAS: 'A420 Revue AAR'!#REF!
Name RAS: 'A430 Revue RFA'!#REF!

Sheet A Synthèse
D1: #NomClient | Q1: OUI
Q2: NON
A3: FOURNISSEURS - ACHATS
Q4: Faible
Q5: Modéré
A6: Fait par : | B6: BRA | C6: Revu par : | E6: Synthèse du cycle | M6: Date Clôture | N6: XRef | Q6: Elevé
A7: Le : | C7: Le : | M7: #DateClôture | N7: A | Q7: PB
Q8: PE
A9: Risque d'anomalies significatives | D9: Modéré | F9: Seuil d'investigation | L9: Niveau de diligences | N9: PE | Q9: PE + VP
A11: Xref | C11: Contrôles | M11: Diligence à tester | N11: Liens
A12: A100 | C12: Rapprochement BA-BG | M12: OUI | N12: A100 Rappro BA-BG
A13: A110 | C13: Revue des fournisseurs débiteurs | M13: OUI | N13: A110 Revue frs débiteurs
A14: A200 | C14: DPO Fournissseurs | M14: OUI | N14: A200 DPO Frs
A15: A300 | C15: Réciprocité intragroupe | M15: OUI | N15: A300 Réciprocité intragroupe
A16: A410 | C16: Revue des FNP | M16: OUI | N16: A410 Revue FNP
A17: A420 | C17: Revue des AAR | M17: OUI | N17: A420 Revue AAR
A18: A430 | C18: Revue des RFA | M18: OUI | N18: A430 Revue RFA
A19: A440 | C19: Revue des CCA | M19: OUI | N19: A440 Revue CCA
A20: A450 | C20: Test de cut-off achats | M20: OUI | N20: A450 Test cut off achats
A21: A500 | C21: Circularisations | M21: OUI | N21: A500 Circularisations
A22: A600 | C22: Revue AACE | M22: OUI | N22: A600 Revue AACE
C23: Revue EAP | M23: NON | N23: A700 Revue EAP
C24: Fournisseurs en devise | M24: NON | N24: A800 Frs en devise
A27: Revue analytique
A28: Cf. A0
A34: CONCLUSION

Sheet A100 Rappro BA-BG
D1: ='A Synthèse'!D1:M2 -> #NomClient
A3: FOURNISSEURS - ACHATS
A6: Fait par : | B6: ='A Synthèse'!B6 -> BRA | C6: Revu par : | D6: ='A Synthèse'!D6 -> 0 | E6: Rapprochement BA-BG | M6: Date Clôture | O6: XRef
A7: Le : | B7: ='A Synthèse'!B7 -> 0 | C7: Le : | D7: ='A Synthèse'!D7 -> 0 | M7: ='A Synthèse'!M7:M7 -> #DateClôture | O7: A100
O8: A Synthèse
A9: Risque d'anomalies significatives | D9: ='A Synthèse'!D9:E9 -> Modéré | F9: Seuil d'investigation | J9: ='A Synthèse'!J9:K9 -> 0 | L9: Niveau de diligences | O9: ='A Synthèse'!N9 -> PE
A11: Objectif : Contrôle de l'exhaustivité des dettes fournisseurs Contrôle de la correcte présentation des comptes entre clients débiteurs et clients créditeurs. Travail effectué Contrôle de la concordance entre la balance auxiliaire et la balance générale. S'assurer que les fournisseurs débiteurs sont bien identifiés et comptabilisés en fournisseurs débiteurs dans les comptes.
A13: Conclusion sur le contrôle
B17: BALANCE AUXILIAIRE | D17: Solde débiteur | E17: Solde créditeur | F17: Solde Net
B18: 401000 - Fournisseurs | F18: =D18-E18 -> 0 | G18: X-Ref
B21: BALANCE GENERALE | D21: Solde débiteur | E21: Solde créditeur | F21: Solde Net
B22: 401000 - Fournisseurs
B23: 401XX
B24: Total | D24: =+SUM(D22:D23) -> 0 | E24: =+SUM(E22:E23) -> 0 | F24: =D24-E24 -> 0 | G24: A0
B26: Ecart | D26: =D18-D24 -> 0 | E26: =E18-E24 -> 0 | F26: =F18-F24 -> 0

Sheet A110 Revue frs débiteurs
D1: ='A Synthèse'!D1:M2 -> #NomClient
A3: FOURNISSEURS - ACHATS
A6: Fait par : | B6: ='A Synthèse'!B6 -> BRA | C6: Revu par : | D6: ='A Synthèse'!D6 -> 0 | E6: Revue fournisseurs débiteurs | M6: Date Clôture | O6: XRef
A7: Le : | B7: ='A Synthèse'!B7 -> 0 | C7: Le : | D7: ='A Synthèse'!D7 -> 0 | M7: ='A Synthèse'!M7:M7 -> #DateClôture | O7: A110
O8: A Synthèse
A9: Risque d'anomalies significatives | D9: ='A Synthèse'!D9:E9 -> Modéré | F9: Seuil d'investigation | J9: ='A Synthèse'!J9:K9 -> 0 | L9: Niveau de diligences | O9: ='A Synthèse'!N9 -> PE
A11: Objectif Présentation des fournisseurs Travail effectué S’assurer qu’il n’existe pas de fournisseurs débiteurs significatifs compensés avec les fournisseurs créditeurs. Le cas échéant proposer le reclassement. Comprendre pourquoi la société comptabilise des fournisseurs débiteurs et vérifier que ces soldes ne sont pas constitutifs d'une anomalie ou d'un litige.
A13: Conclusion sur le contrôle
E17: Débiteurs | F17: Créditeurs
D18: Balance auxiliaire Frs | E18: ='A100 Rappro BA-BG'!D18:D18 -> 0 | F18: ='A100 Rappro BA-BG'!E18:F18 -> 0
D22: Principaux fournisseurs débiteurs | F22: Solde | G22: % des débiteurs | H22: Analyse | N22: X-Ref
G23: =+F23/$E$18 -> #DIV/0!
G24: =+F24/$E$18 -> #DIV/0!
G25: =+F25/$E$18 -> #DIV/0!
G26: =+F26/$E$18 -> #DIV/0!
G27: =+F27/$E$18 -> #DIV/0!
G28: =+F28/$E$18 -> #DIV/0!
G29: =+F29/$E$18 -> #DIV/0!
G30: =+F30/$E$18 -> #DIV/0!
G31: =+F31/$E$18 -> #DIV/0!
G32: =+F32/$E$18 -> #DIV/0!
E33: Total fournisseurs débiteurs testés | F33: =SUM(F23:F32) -> 0 | G33: =+F33/$E$18 -> #DIV/0!

Sheet A200 DPO Frs
D1: ='A Synthèse'!D1:M2 -> #NomClient
A3: FOURNISSEURS - ACHATS
A6: Fait par : | B6: ='A Synthèse'!B6 -> BRA | C6: Revu par : | D6: ='A Synthèse'!D6 -> 0 | E6: DPO Fournisseurs | M6: Date Clôture | O6: XRef
A7: Le : | B7: ='A Synthèse'!B7 -> 0 | C7: Le : | D7: ='A Synthèse'!D7 -> 0 | M7: ='A Synthèse'!M7:M7 -> #DateClôture | O7: A200
O8: A Synthèse
A9: Risque d'anomalies significatives | D9: ='A Synthèse'!D9:E9 -> Modéré | F9: Seuil d'investigation | J9: ='A Synthèse'!J9:K9 -> 0 | L9: Niveau de diligences | O9: ='A Synthèse'!N9 -> PE
A11: Objectif Analyse de l'évolution de l'encours frs Travail effectué A partir des derniers journaux d'achats de l'exercice et du solde frs à la clôture, calculer le délai de règlement des frs à la clôture de l'exercice. Pour rappel, la règle LME s'applique aux frs externes français et étrangers et aux frs intragroupe. Il n'est donc pas nécessaire de procéder à un retraitement de ces dettes lors du calcul du délai. Revue analytique N / N-1 Comparaison avec les habitudes de paiement de la société (délai théorique) Comparaison avec les obligations de la LME
A13: Conclusion sur le contrôle
D17: Total fournisseurs | E17: N | F17: N-1
D19: Frs
D20: EAP (si inclus dans jal achats)
D23: TOTAL | E23: =SUM(E19:E21) -> 0 | F23: =SUM(F19:F21) -> 0
D25: Variation | E25: =E23-F23 -> 0
I26: Nombre | J26: Nombre
I27: de jours | J27: de jours
D28: Journaux d'achats mensuels TTC | E28: =E17 -> N | F28: =F17 -> N-1 | I28: N | J28: N-1
D30: M | I30: 31 | J30: 31
D31: M-1 | I31: 30 | J31: 30
D32: M-2 | I32: 31 | J32: 31
D36: TOTAL | E36: =SUM(E30:E34) -> 0 | F36: =SUM(F30:F34) -> 0
D39: Nombre de jours | E39: =E17 -> N | F39: =F17 -> N-1 | I39: RESTE N | J39: N-1
D41: =D30 -> M | E41: =IF(E30="","",IF(E23>E30,I30,E23*I30/E30)) | F41: =IF(F30="","",IF(F23>F30,J30,F23*J30/F30)) | I41: =IF($E$23-$E$30>0,$E$23-$E$30,0) -> 0 | J41: =IF(F23-F30>0,F23-F30,0) -> 0
D42: =D31 -> M-1 | E42: =IF(E31="","",IF(I41>E31,I31,I41*I31/E31)) | F42: =IF(F31="","",IF(J41>F31,J31,J41*J31/F31)) | I42: =IF($I$41-$E$31>0,$I$41-$E$31,0) -> 0 | J42: =IF(J41-$F$31>0,J41-$F$31,0) -> 0
D43: =D32 -> M-2 | E43: =IF(E32="","",IF(I42>E32,I32,I42*I32/E32)) | F43: =IF(F32="","",IF(J42>F32,J32,J42*J32/F32)) | I43: =IF($I$42-$E$32>0,$I$42-$E$32,0) -> 0 | J43: =IF(J42-$F$32>0,J42-$F$32,0) -> 0
F44: =IF(F33="","",IF(J43>F33,J33,J43*J33/F33))
F45: =IF(F34="","",IF(J44>F34,J34,J44*J34/F34))
G47: Var
B48: Délai FIFO | E48: =SUM(E41:E45) -> 0 | F48: =SUM(F41:F45) -> 0 | G48: =E48-F48 -> 0 | I48: Effet activité | J48: =(G49*E48) -> #DIV/0!
B49: CA/JOUR | E49: =+E23/E48 -> #DIV/0! | F49: =+F23/F48 -> #DIV/0! | G49: =+E49-F49 -> #DIV/0! | I49: Effet délai | J49: =G48*F49 -> #DIV/0!
I50: Total effets | J50: =SUM(J48:J49) -> #DIV/0!
A52: Rappel de la LME : Les délais de paiement entre professionnels sont réglementés : sans dispositions contraires figurant aux conditions de vente ou convenues entre les parties, le délai de règlement est fixé au 30e jour suivant la réception des marchandises ou l'exécution de la prestation. Mais s'il est précisé au contrat, le délai peut aller au-delà des 30 jours, sans dépasser 45 jours jours fin de mois (ou 60 jours à partir de la facturation). Des dérogations existent pour les produits périssables. Mise à jour le 17.09.2014 - Direction de l'information légale et administrative (Premier ministre) http://vosdroits.service-public.fr/professionnels-entreprises/F23211.xhtml

Sheet A300 Réciprocité intragroupe
D1: ='A Synthèse'!D1:M2 -> #NomClient
A3: FOURNISSEURS - ACHATS
A6: Fait par : | B6: ='A Synthèse'!B6 -> BRA | C6: Revu par : | D6: ='A Synthèse'!D6 -> 0 | E6: Réciprocité intragroupe | M6: Date Clôture | O6: XRef
A7: Le : | B7: ='A Synthèse'!B7 -> 0 | C7: Le : | D7: ='A Synthèse'!D7 -> 0 | M7: ='A Synthèse'!M7:M7 -> #DateClôture | O7: A300
O8: A Synthèse
A9: Risque d'anomalies significatives | D9: ='A Synthèse'!D9:E9 -> Modéré | F9: Seuil d'investigation | J9: ='A Synthèse'!J9:K9 -> 0 | L9: Niveau de diligences | O9: ='A Synthèse'!N9 -> PE
A11: Objectif Contrôler l'exhaustivité des soldes frs interco Travail effectué A partir des soldes interco, contrôler la réciprocité des encours avec ceux de la balance frs de ces mêmes sociétés.
A13: Conclusion sur le contrôle
F17: Solde chez X | I17: Solde chez intercos | L17: Ecart
F18: débit | G18: X-Ref BA | H18: crédit | I18: débit | J18: crédit | K18: X-Ref BA
D19: A | L19: =F19-J19 -> 0
D20: B | L20: =F20-J20 -> 0
D21: C | L21: =F21-J21 -> 0
D22: D | L22: =F22-J22 -> 0

Sheet A410 Revue FNP
D1: ='A Synthèse'!D1:M2 -> #NomClient
A3: FOURNISSEURS - ACHATS
A6: Fait par : | B6: ='A Synthèse'!B6 -> BRA | C6: Revu par : | D6: ='A Synthèse'!D6 -> 0 | E6: Revue FNP | M6: Date Clôture | O6: XRef
A7: Le : | B7: ='A Synthèse'!B7 -> 0 | C7: Le : | D7: ='A Synthèse'!D7 -> 0 | M7: ='A Synthèse'!M7:M7 -> #DateClôture | O7: A410
O8: A Synthèse
A9: Risque d'anomalies significatives | D9: ='A Synthèse'!D9:E9 -> Modéré | F9: Seuil d'investigation | J9: ='A Synthèse'!J9:K9 -> 0 | L9: Niveau de diligences | O9: ='A Synthèse'!N9 -> PE
A11: Objectif Exhaustivité et évaluation des FNP Travail effectué Obtenir les détails des comptes de FNP et les cadrer avec la balance générale et effectuer les contrôles arithmétiques nécessaires. Procéder par revue analytique : identifier les principales FNP et identifier si ce sont des éléments récurrents notamment des frais généraux (à partir des détails N-1). Investiguer notamment en cas d'absence de FNP que l'on sait de nature récurrente. Selon l'approche d'audit retenue sur le dossier (en lien notamment avec l'assurance que l'on a sur le process Frs/Achats et les autres tests de détail menés sur les fournisseurs notamment le cut off), cette revue analytique peut être suffisante pour valider l'exhaustivité et l'exactitude des FNP. Pour les FNP > SI, obtenir les justificatifs : factures émises sur la période subséquente et si nécessaires bons de livraisons / réalisation des prestations… Croiser ce test avec les travaux réalisés sur le cut off et les circularisations frs notamment.
A13: Conclusion sur le contrôle
A17: a) Revue analytique des FNP :
A19: Nature des FNP | D19: 31/12/N | E19: 31/12/N-1 | F19: Var | G19: Var % | H19: Caractère récurrent | I19: Ref pièce | J19: Analyse
F20: =D20-E20 -> 0 | G20: =F20/E20 -> #DIV/0!
F21: =D21-E21 -> 0 | G21: =F21/E21 -> #DIV/0!
F22: =D22-E22 -> 0 | G22: =F22/E22 -> #DIV/0!
F23: =D23-E23 -> 0 | G23: =F23/E23 -> #DIV/0!
F24: =D24-E24 -> 0 | G24: =F24/E24 -> #DIV/0!
F25: =D25-E25 -> 0 | G25: =F25/E25 -> #DIV/0!
F26: =D26-E26 -> 0 | G26: =F26/E26 -> #DIV/0!
C27: TOTAL | D27: =SUM(D20:D26) -> 0 | E27: =SUM(E20:E26) -> 0 | F27: =SUM(F20:F26) -> 0 | G27: =+F27/E27 -> #DIV/0!
A29: b) Test de détail sur les FNP :
A31: Fournisseur | C31: N° facture | D31: N° facture | E31: Date facturation | F31: Montant HT | G31: Date de la prestation ou réception | H31: N° BL | I31: Ref pièce | J31: Observations
D36: Population testée | F36: =SUM(F32:F35) -> 0
D37: Population totale
D38: % Testé | F38: =F36/F37 -> #DIV/0!

Sheet A420 Revue AAR
D1: ='A Synthèse'!D1:M2 -> #NomClient
A3: FOURNISSEURS - ACHATS
A6: Fait par : | B6: ='A Synthèse'!B6 -> BRA | C6: Revu par : | D6: ='A Synthèse'!D6 -> 0 | E6: Revue AAR | M6: Date Clôture | O6: XRef
A7: Le : | B7: ='A Synthèse'!B7 -> 0 | C7: Le : | D7: ='A Synthèse'!D7 -> 0 | M7: ='A Synthèse'!M7:M7 -> #DateClôture | O7: A420
O8: A Synthèse
A9: Risque d'anomalies significatives | D9: ='A Synthèse'!D9:E9 -> Modéré | F9: Seuil d'investigation | J9: ='A Synthèse'!J9:K9 -> 0 | L9: Niveau de diligences | O9: ='A Synthèse'!N9 -> PE
A11: Objectif Réalité et évaluation des AAR Travail effectué Obtenir les détails des comptes de AAR et les cadrer avec la balance générale et effectuer les contrôles arithmétiques nécessaires. Procéder par revue analytique : identifier les principaux AAR et identifier si ce sont des éléments récurrents (à partir des détails N-1), la nature des AAR (avoirs sur factures, RFA,...). Investiguer notamment en cas d'absence d'AAR que l'on sait de nature récurrente. Selon l'approche d'audit retenue sur le dossier (en lien notamment avec l'assurance que l'on a sur le process Frs/Achats et les autres tests de détail menés sur les frs notamment le cut off), cette revue analytique peut être suffisante pour contrôler la réalité et l'exactitude des AAR. Pour les AAR > SI, obtenir les justificatifs : avoirs émis sur la période subséquente A partir du journal d'achat de janvier N+1 sélection des avoirs HT > à SI et contrôle de la nécessité de provisionner un AAR à la clôture.
A13: Conclusion sur le contrôle
A17: a) Revue analytique des AAR :
A19: Principaux AAR | D19: 31/12/N | E19: 31/12/N-1 | F19: Var | G19: Var % | H19: Caractère récurrent | I19: Ref pièce | J19: Analyse
F20: =D20-E20 -> 0 | G20: =F20/E20 -> #DIV/0!
F21: =D21-E21 -> 0 | G21: =F21/E21 -> #DIV/0!
F22: =D22-E22 -> 0 | G22: =F22/E22 -> #DIV/0!
F23: =D23-E23 -> 0 | G23: =F23/E23 -> #DIV/0!
C24: TOTAL | D24: =SUM(D20:D23) -> 0 | E24: =SUM(E20:E23) -> 0 | F24: =SUM(F20:F23) -> 0 | G24: =+F24/E24 -> #DIV/0!
A26: b) Test de détail sur les AAR :
A28: Frs | C28: N° facture | D28: Date facturation | E28: Montant HT | F28: Date de la prestation ou réception | G28: N° BL | H28: Ref pièce | I28: Observations
C33: Population testée | E33: =SUM(E29:E32) -> 0
C34: Population totale
C35: % Testé | E35: =E33/E34 -> #DIV/0!
A39: c/ Tests sur les journaux d'achats post-clôture
A41: Ref avoir | B41: Fournisseurs | E41: Nature | F41: HT | G41: TVA | H41: TTC | I41: Nécessité d'une provision AAR | J41: Commentaires | Q41: OUI
H42: =F42*(1+G42) -> 0 | Q42: NON
H43: =F43*(1+G43) -> 0
H44: =F44*(1+G44) -> 0
H45: =F45*(1+G45) -> 0
H46: Total testé = | I46: =SUM(H42:H45) -> 0
H47: Total des AAR =
H48: Scope de test = | I48: =I46/I47 -> #DIV/0!

Sheet A430 Revue RFA
D1: ='A Synthèse'!D1:M2 -> #NomClient
A3: FOURNISSEURS - ACHATS
A6: Fait par : | B6: ='A Synthèse'!B6 -> BRA | C6: Revu par : | D6: ='A Synthèse'!D6 -> 0 | E6: Revue RFA | M6: Date Clôture | O6: XRef
A7: Le : | B7: ='A Synthèse'!B7 -> 0 | C7: Le : | D7: ='A Synthèse'!D7 -> 0 | M7: ='A Synthèse'!M7:M7 -> #DateClôture | O7: A430
O8: A Synthèse
A9: Risque d'anomalies significatives | D9: ='A Synthèse'!D9:E9 -> Modéré | F9: Seuil d'investigation | J9: ='A Synthèse'!J9:K9 -> 0 | L9: Niveau de diligences | O9: ='A Synthèse'!N9 -> PE
A11: Objectif Réalité et évaluation des RFA Travail effectué 1/ Après entretien avec la Direction et des travaux N-1, comprendre si la société perçoit ou non les RFA (remises de fin d'année). ==> Rappel de la politique de la société vis-à-vis des RFA perçues. Si oui, s'assurer qu'elle comptabilise/provisionne bien ces RFA à la clôture de l'exercice audité. 2/ Revue analytique des RFA N/N-1 et calcul du taux moyen de RFA sur les deux exercices. 3/ Si Revue analytique et taux de RFA moyen sur l'année non cohérents (2/), procéder à des test de détail sur les RFA. S'assurer que les taux utilisés sont conformes aux contrats (s'il y en a) ou autre élément de preuve (mails, entretien avec la Direction, …). S'assurer en outre que la base de CA annuel utilisée pour calculer ces RFA est conforme au CA réalisé en stat commerciale. 4/ Dans tous les cas, vérifier sur N l'apurement des RFA comptabilisées en N-1, permettant de contrôler la méthode.
A13: Conclusion sur le contrôle
A17: 1/ Liste des fournisseurs concernés et termes des accords
C19: Fournisseurs | D19: Termes du contrat | E19: X-Ref
A27: 2/ Revue analytique des RFA N/N-1 et calcul du taux moyen de RFA sur les deux exercices
C29: Fournisseurs | E29: 31/12/N | F29: 31/12/N-1 | G29: Var | H29: Var %
G30: =E30-F30 -> 0 | H30: =G30/F30 -> #DIV/0!
G31: =E31-F31 -> 0 | H31: =G31/F31 -> #DIV/0!
G32: =E32-F32 -> 0 | H32: =G32/F32 -> #DIV/0!
G33: =E33-F33 -> 0 | H33: =G33/F33 -> #DIV/0!
G34: =E34-F34 -> 0 | H34: =G34/F34 -> #DIV/0!
C35: Total RFA HT annuelles | E35: =SUM(E30:E34) -> 0 | F35: =SUM(F30:F34) -> 0 | G35: =+E35-F35 -> 0 | H35: =G35/F35 -> #DIV/0!
B37: Montant annuel du CA HT net | G37: =E37-F37 -> 0 | H37: =G37/F37 -> #DIV/0!
B39: Taux moyen annuel de RFA | E39: =E35/E37 -> #DIV/0! | F39: =F35/F37 -> #DIV/0! | G39: =E39-F39 -> #DIV/0!
A42: Revue analytique des RFA
A46: 3/ Test sur des RFA comptabilisées à la clôture de l'exercice (optionnel si Revue analytique et taux de RFA moyen sur l'année non cohérents)
A48: Fournisseurs | C48: Base du CA issu stat commerciale N | D48: Taux RFA | E48: RFA à comptabiliser à la clôture | F48: RFA en compta à la clôture | G48: Ecart | H48: Commentaire
E49: =C49*D49 -> 0 | G49: =F49-E49 -> 0
E50: =C50*D50 -> 0 | G50: =F50-E50 -> 0
E51: =C51*D51 -> 0 | G51: =F51-E51 -> 0
E52: =C52*D52 -> 0 | G52: =F52-E52 -> 0
A56: 4/ Contrôle de l'apurement des RFA N-1 (A faire dans tous les cas)
A58: Fournisseurs | C58: RFA provisionnées en N-1 | D58: RFA accordées/perçues en N | E58: Ecart | F58: Commentaire
E59: =C59-D59 -> 0
E60: =C60-D60 -> 0
E61: =C61-D61 -> 0
E62: =C62-D62 -> 0

Sheet A440 Revue CCA
D1: ='A Synthèse'!D1:M2 -> #NomClient
A3: FOURNISSEURS - ACHATS
A6: Fait par : | B6: ='A Synthèse'!B6 -> BRA | C6: Revu par : | D6: ='A Synthèse'!D6 -> 0 | E6: Revue CCA | M6: Date Clôture | O6: XRef
A7: Le : | B7: ='A Synthèse'!B7 -> 0 | C7: Le : | D7: ='A Synthèse'!D7 -> 0 | M7: ='A Synthèse'!M7:M7 -> #DateClôture | O7: A440
O8: A Synthèse
A9: Risque d'anomalies significatives | D9: ='A Synthèse'!D9:E9 -> Modéré | F9: Seuil d'investigation | J9: ='A Synthèse'!J9:K9 -> 0 | L9: Niveau de diligences | O9: ='A Synthèse'!N9 -> PE
A11: Objectif Exhaustivité et évaluation des charges constatées d'avance Travail effectué Obtenir le détail des CCA et le rapprocher de la comptabilité Effectuer des tests justifiant la correcte évaluation des CCA provisionnés Effectuer un comparatif par grandes masses avec les CCA de l'exercice précédent et expliquer les principales évolutions
A13: Conclusion sur le contrôle
A17: a) Revue analytique des CCA :
A19: Nature des CCA | D19: 31/12/N | E19: 31/12/N-1 | F19: Var | G19: Var % | H19: Caractère récurrent | I19: Ref pièce | J19: Analyse
F20: =D20-E20 -> 0 | G20: =F20/E20 -> #DIV/0!
F21: =D21-E21 -> 0 | G21: =F21/E21 -> #DIV/0!
F22: =D22-E22 -> 0 | G22: =F22/E22 -> #DIV/0!
F23: =D23-E23 -> 0 | G23: =F23/E23 -> #DIV/0!
F24: =D24-E24 -> 0 | G24: =F24/E24 -> #DIV/0!
F25: =D25-E25 -> 0 | G25: =F25/E25 -> #DIV/0!
F26: =D26-E26 -> 0 | G26: =F26/E26 -> #DIV/0!
C27: TOTAL | D27: =SUM(D20:D26) -> 0 | E27: =SUM(E20:E26) -> 0 | F27: =SUM(F20:F26) -> 0 | G27: =+F27/E27 -> #DIV/0!
A29: b) Test de détail sur les CCA :
A31: Fournisseur | C31: N° facture | D31: N° facture | E31: Date facturation | F31: Montant HT | G31: Date de la prestation ou réception | H31: N° BL | I31: Ref pièce | J31: Observations
D36: Population testée | F36: =SUM(F32:F35) -> 0
D37: Population totale
D38: % Testé | F38: =F36/F37 -> #DIV/0!

Sheet A450 Test cut off achats
D1: ='A Synthèse'!D1:M2 -> #NomClient
A3: FOURNISSEURS - ACHATS
A6: Fait par : | B6: ='A Synthèse'!B6 -> BRA | C6: Revu par : | D6: ='A Synthèse'!D6 -> 0 | E6: Test cut off achats | M6: Date Clôture | O6: XRef
A7: Le : | B7: ='A Synthèse'!B7 -> 0 | C7: Le : | D7: ='A Synthèse'!D7 -> 0 | M7: ='A Synthèse'!M7:M7 -> #DateClôture | O7: A450
O8: A Synthèse
A9: Risque d'anomalies significatives | D9: ='A Synthèse'!D9:E9 -> Modéré | F9: Seuil d'investigation | J9: ='A Synthèse'!J9:K9 -> 0 | L9: Niveau de diligences | O9: ='A Synthèse'!N9 -> PE
A11: Objectif S'assurer du respect du principe de séparation des exercices Travail effectué Sélection de factures HT > SI Rapprochement aux justificatifs : facture + date de comptabilisation de la facture + BR ou bon de transports émargés/date de prestation En fonction du sens du risque (tendance de la société à majorer ou à minorer son résultat), effectuer un des deux tests suivants : 1/ Revue des achats de décembre N (en cas de tendance à la minoration du résultat) 2/ Revue des achats de janvier N (en cas de tendance à la majoration du résultat) Vigilance : incoterms
A13: Conclusion sur le contrôle
A17: 1/ Dernier mois de l'exercice N
A19: Date de facture | B19: Fournisseurs | D19: Facture N° | E19: Montant de la facture TTC | F19: Date du BR ou date PS | G19: Conclusion | P19: X-ref
D31: Total testé = | E31: =SUM(E20:E30) -> 0
D32: Total journal =
D33: Scope de test = | E33: =E31/E32 -> #DIV/0!
A37: 2/ Premier mois de l'exercice N+1
A39: Date de facture | B39: Fournisseurs | D39: Facture N° | E39: Montant de la facture TTC | F39: Date du BR ou date PS | G39: Conclusion | P39: X-ref
D51: Total testé = | E51: =SUM(E40:E50) -> 0
D52: Total journal =
D53: Scope de test = | E53: =E51/E52 -> #DIV/0!

Sheet A500 Circularisations
D1: ='A Synthèse'!D1:M2 -> #NomClient
A3: FOURNISSEURS - ACHATS
A6: Fait par : | B6: ='A Synthèse'!B6 -> BRA | C6: Revu par : | D6: ='A Synthèse'!D6 -> 0 | E6: Circularisations | M6: Date Clôture | O6: XRef
A7: Le : | B7: ='A Synthèse'!B7 -> 0 | C7: Le : | D7: ='A Synthèse'!D7 -> 0 | M7: ='A Synthèse'!M7:M7 -> #DateClôture | O7: A500
O8: A Synthèse
A9: Risque d'anomalies significatives | D9: ='A Synthèse'!D9:E9 -> Modéré | F9: Seuil d'investigation | J9: ='A Synthèse'!J9:K9 -> 0 | L9: Niveau de diligences | O9: ='A Synthèse'!N9 -> PE
A11: Objectif Exhaustivité des encours frs par circularisation des tiers Travail effectué 1/ A partir de la balance auxiliaire provisioire en date du XX/XX/XXXX, sélectionner les mouvements créditeurs les plus significatifs (cf. procédure circularisations dans Sharepoint) 2/ Emettre des courriers de demande de confirmation de soldes 3/ Exploiter les réponses de circularisations reçues 4/ En cas de non réponse, mise en place de la procédire alternative (à partir de l'extrait de GL fournisseur, sélection des factures significatives et retour sur pièces)7
A13: Conclusion sur le contrôle
A17: 1° Critères de sélections
A19: cf. fichier sélection auto circul
A23: 2° Tableau de synthèse des circularisations
D25: Comptabilité | E25: Justification du solde | I25: Justification du solde des mouvements créditeurs
A26: X Ref | B26: Numéro et Nom du fournisseur | D26: Solde Frs à la clôture (BA) | E26: Solde confirmé par le tiers | F26: Ecart | G26: Ecart justifié | H26: Ecart non justifié | I26: Total mvt créditeur à la clôture | J26: Total des mvt confirmé | K26: Ecart | L26: Ecart justifié | M26: Ecart non justifié | N26: Analyse
F27: =D27-E27 -> 0 | H27: =F27-G27 -> 0 | K27: =I27-J27 -> 0 | M27: =K27-L27 -> 0
F28: =D28-E28 -> 0 | H28: =F28-G28 -> 0 | K28: =I28-J28 -> 0 | M28: =K28-L28 -> 0
F29: =D29-E29 -> 0 | H29: =F29-G29 -> 0 | K29: =I29-J29 -> 0 | M29: =K29-L29 -> 0
F30: =D30-E30 -> 0 | H30: =F30-G30 -> 0 | K30: =I30-J30 -> 0 | M30: =K30-L30 -> 0
F31: =D31-E31 -> 0 | H31: =F31-G31 -> 0 | K31: =I31-J31 -> 0 | M31: =K31-L31 -> 0
F32: =D32-E32 -> 0 | H32: =F32-G32 -> 0 | K32: =I32-J32 -> 0 | M32: =K32-L32 -> 0
F33: =D33-E33 -> 0 | H33: =F33-G33 -> 0 | K33: =I33-J33 -> 0 | M33: =K33-L33 -> 0
F34: =D34-E34 -> 0 | H34: =F34-G34 -> 0 | K34: =I34-J34 -> 0 | M34: =K34-L34 -> 0
F35: =D35-E35 -> 0 | H35: =F35-G35 -> 0 | K35: =I35-J35 -> 0 | M35: =K35-L35 -> 0
A37: Total sélection solde créditeurs = | D37: =SUM(D27:D35) -> 0 | F37: Total sélection mvt créditeurs = | I37: =SUM(I27:I35) -> 0
A39: Total balance solde créditeurs = | D39: ='A100 Rappro BA-BG'!E18 -> 0 | F39: Total balance mvt créditeurs =
A41: % sélection solde créditeurs = | D41: =D37/D39 -> #DIV/0! | F41: % sélection mvt créditeurs = | I41: =I37/I39 -> #DIV/0!
A45: 3°Procédures alternatives fournisseurs
D47: Comptabilité | F47: Méthode de test | H47: Résultat
A48: X Ref sélection | B48: Numéro et Nom du fournisseur | D48: Solde Frs à la clôture (BA) | E48: Total mvt créditeur à la clôture | F48: Nombre de factures sélectionné | G48: Factures sélectionnées > à | H48: Total montant testé | I48: Scope | J48: Analyse
I49: =H49/E49 -> #DIV/0!
I50: =H50/E50 -> #DIV/0!
I51: =H51/E51 -> #DIV/0!
I52: =H52/E52 -> #DIV/0!
I53: =H53/E53 -> #DIV/0!
I54: =H54/E54 -> #DIV/0!
I55: =H55/E55 -> #DIV/0!
I56: =H56/E56 -> #DIV/0!
I57: =H57/E57 -> #DIV/0!

Sheet A600 Revue AACE
D1: ='A Synthèse'!D1:M2 -> #NomClient
A3: FOURNISSEURS - ACHATS
A6: Fait par : | B6: ='A Synthèse'!B6 -> BRA | C6: Revu par : | D6: ='A Synthèse'!D6 -> 0 | E6: Revue AACE | M6: Date Clôture | O6: XRef
A7: Le : | B7: ='A Synthèse'!B7 -> 0 | C7: Le : | D7: ='A Synthèse'!D7 -> 0 | M7: ='A Synthèse'!M7:M7 -> #DateClôture | O7: A600
O8: A Synthèse
A9: Risque d'anomalies significatives | D9: ='A Synthèse'!D9:E9 -> Modéré | F9: Seuil d'investigation | J9: ='A Synthèse'!J9:K9 -> 0 | L9: Niveau de diligences | O9: ='A Synthèse'!N9 -> PE
A11: Objectif Exhaustivité et évaluation des autres charges externes Travail effectué Revue analytique des charges : comprendre les variations par grands postes de charges. Cadrage des prestations facturées avec les conventions (groupes) signées. Retour sur les pièces justificatives pour les postes à fortes variations. S'assurer que la variation est cohérante avec l'analyse de l'activité, éventuellement au moyen de ratios pertinents (commissions / ventes ou achats, frais de ports / CA, énergie / activité…).
A13: Conclusion sur le contrôle
A32: 1° Revue analytique des AACE
A33: Cf. A610 AACE

Sheet A700 Revue EAP
D1: ='A Synthèse'!D1:M2 -> #NomClient
A3: FOURNISSEURS - ACHATS
A6: Fait par : | B6: ='A Synthèse'!B6 -> BRA | C6: Revu par : | D6: ='A Synthèse'!D6 -> 0 | E6: Revue EAP | M6: Date Clôture | O6: XRef
A7: Le : | B7: ='A Synthèse'!B7 -> 0 | C7: Le : | D7: ='A Synthèse'!D7 -> 0 | M7: ='A Synthèse'!M7:M7 -> #DateClôture | O7: A700
O8: A Synthèse
A9: Risque d'anomalies significatives | D9: ='A Synthèse'!D9:E9 -> Modéré | F9: Seuil d'investigation | J9: ='A Synthèse'!J9:K9 -> 0 | L9: Niveau de diligences | O9: ='A Synthèse'!N9 -> PE
A11: Objectif Contrôle de l'évaluation et de la présentation des effets à payer Travail effectué Rapprocher la comptabilité du détail des effets à payer par date d’échéance - contrôle apurement des EAP si l'antériorité n'est pas satisfaisante. S’assurer que tous les effets à payer sont à échéance post clôture, dans le cas contraire proposer le reclassement
A13: Conclusion sur le contrôle
A17: 1° Rapprochemenent Balance générale / état des EAP
A19: Montant des effets à payer en comptabilité
A21: Etat des effets à payer à la clôture
A23: écart | D23: =D19-D21 -> 0
A26: 2° Test de détail : contrôle antériorité des EAP
A28: Nom fournisseurs | D28: Solde | E28: Antériorité | F28: Apurement | G28: X-Réf | H28: Remarques
C44: Total Sélection Fournisseurs - Effets à payer | D44: =SUM(D29:D42) -> 0
C46: Total Fournisseurs - Effets à payer
C48: % de contrôle | D48: =+D44/D46 -> #DIV/0!
A51: 3° Test de cut off sur les EAP
A53: A partir du grand-livre des effet à payer, contrôle de l'absence d'effet dont la date d'échéance est antérieure à la clôture
A54: A défaut proposer le reclassement en #512 et sa neutralisation en ERB
A56: Conclusion sur le contrôle

Sheet A800 Frs en devise
D1: ='A Synthèse'!D1:M2 -> #NomClient
A3: FOURNISSEURS - ACHATS
A6: Fait par : | B6: ='A Synthèse'!B6 -> BRA | C6: Revu par : | D6: ='A Synthèse'!D6 -> 0 | E6: Fournisseurs en devise | M6: Date Clôture | O6: XRef
A7: Le : | B7: ='A Synthèse'!B7 -> 0 | C7: Le : | D7: ='A Synthèse'!D7 -> 0 | M7: ='A Synthèse'!M7:M7 -> #DateClôture | O7: A800
O8: A Synthèse
A9: Risque d'anomalies significatives | D9: ='A Synthèse'!D9:E9 -> Modéré | F9: Seuil d'investigation | J9: ='A Synthèse'!J9:K9 -> 0 | L9: Niveau de diligences | O9: ='A Synthèse'!N9 -> PE
A11: Objectif S'assurer de la correcte évaluation des dettes libellées en devise à la clôture de l'exercice. Travail effectué 1) obtenir la liste des fournisseurs pour lesquels un risque de conversion existe (Encours avec une facturation en devises hors euros) 2) Vérifier la cohérence du taux de conversion utilisé par l'entité 3) Vérifier la correcte comptabilisation de la réévaluation (réévaluation de la dette et constatation d'un ECA/ECP) 4) S'assurer que les écarts de conversion actifs ont fait l'objet d'une provision pour risques si nécessaire 5) S'assurer que les profits de change latents sont réintégrés pour la détermination du résultat fiscal
A13: Conclusion sur le contrôle
A17: 1° Liste des fournisseurs facturés au moins partiellement en devise et
A18: 2° Cohérence des taux de conversion utilisés par l'entité
A20: N° compte frs | B20: Nom du frs | C20: Devise de facturation | D20: Solde en euros à la date de clôture (issu BA) | E20: X-Ref | F20: Taux de change utilisé | G20: Taux de change à la clôture (issu BDF) | H20: X-Ref | I20: Ecart | J20: Impact résultat | K20: Conclusion
I23: =F23-G23 -> 0 | J23: =D23*I23 -> 0
I24: =F24-G24 -> 0 | J24: =D24*I24 -> 0
I25: =F25-G25 -> 0 | J25: =D25*I25 -> 0
I26: =F26-G26 -> 0 | J26: =D26*I26 -> 0
I27: =F27-G27 -> 0 | J27: =D27*I27 -> 0
I28: =F28-G28 -> 0 | J28: =D28*I28 -> 0
I29: =F29-G29 -> 0 | J29: =D29*I29 -> 0
I30: =F30-G30 -> 0 | J30: =D30*I30 -> 0
I31: =F31-G31 -> 0 | J31: =D31*I31 -> 0
I32: =F32-G32 -> 0 | J32: =D32*I32 -> 0
A35: 3° Correcte comptabilisation de la réévaluation (réévaluation de la créance et constatation d'un ECA/ECP)
A37: N° compte frs | B37: Nom du frs | C37: Solde en euros à la date de clôture (issu BA) | D37: Devise | G37: E.C.A | H37: E.C.P | I37: Conclusion
D38: Solde en devise | E38: Taux de clôture | F38: Solde réévalué
F40: =D40*E40 -> 0 | G40: =IF(F40>C40,F40 - C40,"N/A") -> N/A | H40: =IF(F40<C40,F40 - C40,"N/A") -> N/A
F41: =D41*E41 -> 0 | G41: =IF(F41>C41,F41 - C41,"N/A") -> N/A | H41: =IF(F41<C41,F41 - C41,"N/A") -> N/A
F42: =D42*E42 -> 0 | G42: =IF(F42>C42,F42 - C42,"N/A") -> N/A | H42: =IF(F42<C42,F42 - C42,"N/A") -> N/A
F43: =D43*E43 -> 0 | G43: =IF(F43>C43,F43 - C43,"N/A") -> N/A | H43: =IF(F43<C43,F43 - C43,"N/A") -> N/A
F44: =D44*E44 -> 0 | G44: =IF(F44>C44,F44 - C44,"N/A") -> N/A | H44: =IF(F44<C44,F44 - C44,"N/A") -> N/A
F45: =D45*E45 -> 0 | G45: =IF(F45>C45,F45 - C45,"N/A") -> N/A | H45: =IF(F45<C45,F45 - C45,"N/A") -> N/A
F46: =D46*E46 -> 0 | G46: =IF(F46>C46,F46 - C46,"N/A") -> N/A | H46: =IF(F46<C46,F46 - C46,"N/A") -> N/A
F47: =D47*E47 -> 0 | G47: =IF(F47>C47,F47 - C47,"N/A") -> N/A | H47: =IF(F47<C47,F47 - C47,"N/A") -> N/A
F48: =D48*E48 -> 0 | G48: =IF(F48>C48,F48 - C48,"N/A") -> N/A | H48: =IF(F48<C48,F48 - C48,"N/A") -> N/A
F49: =D49*E49 -> 0 | G49: =IF(F49>C49,F49 - C49,"N/A") -> N/A | H49: =IF(F49<C49,F49 - C49,"N/A") -> N/A
F50: =D50*E50 -> 0 | G50: =IF(F50>C50,F50 - C50,"N/A") -> N/A | H50: =IF(F50<C50,F50 - C50,"N/A") -> N/A
F51: =D51*E51 -> 0 | G51: =IF(F51>C51,F51 - C51,"N/A") -> N/A | H51: =IF(F51<C51,F51 - C51,"N/A") -> N/A
... F55: =D55*E55 -> 0 | G55: =IF(F55>C55,F55 - C55,"N/A") -> N/A | H55: =IF(F55<C55,F55 - C55,"N/A") -> N/A
