Workbook
Name ça: "$#REF !.$B$508:$R$508"
Name CA_N: [1]SIG!$B$8
Name CA_N_1: [1]SIG!$D$8
Name çb: "$#REF !.$A$48:$K$48"
Name çi: "$#REF !.$R$11:$R$508"
Name cloture: "$#REF !.$G$9"
Name çp: "$#REF !.$B$44:$F$44"
Name çr: "$#REF !.$B$62:$H$62"
Name çs: "$#REF !.$B$161:$L$161"
Name dateCloture: #REF!
Name dateCloture: #REF!
Name dateCloture: #REF!
Name dateCloture: #REF!
Name DatesCloture: "$#REF !.$F$9:$#REF !.$M$9"
Name Diligences: 'I Synthèse'!$Q$7:$Q$9
Name Diligences: 'I850 Titres et créances ratta'!#REF!
Name Diligences: 'I900 Autres immos fi.'!#REF!
Name Diligences: '[2]I Synthèse'!$R$7:$R$9
Name Etat: 'I Synthèse'!$Q$1:$Q$3
Name Etat: 'I850 Titres et créances ratta'!#REF!
Name Etat: 'I900 Autres immos fi.'!#REF!
Name Etat: '[2]I Synthèse'!$R$1:$R$3
Name NomDossier: "$#REF !.$E$1"
Name RAS: 'I Synthèse'!$Q$4:$Q$6
Name RAS: 'I850 Titres et créances ratta'!#REF!
Name RAS: 'I900 Autres immos fi.'!#REF!
Name RAS: '[2]I Synthèse'!$R$4:$R$6
Name referenceDossier: #REF!
Name referenceDossier: #REF!
Name referenceDossier: #REF!
Name referenceDossier: #REF!
Name sold6037: "$#REF !.$A$85:$I$85"
Name sold607: "$#REF !.$A$84:$I$84"
Name sold701: "$#REF !.$A$73:$I$73"
Name sold706: "$#REF !.$A$74:$I$74"
Name sold707: "$#REF !.$A$72:$I$72"
Name sold71: "$#REF !.$A$75:$I$75"
Name sold781: "$#REF !.$A$151:$I$151"
Name sold791: "$#REF !.$A$82:$I$82"
Name soldesCapitaux: "$#REF !.$A$55:$J$66"
Name start_toc: #REF!
Name start_toc: #REF!
Name start_toc: #REF!
Name start_toc: #REF!
Name TOTAL1_N: '[1]BILAN PASSIF'!$F$24
Name TOTAL1_N_1: '[1]BILAN PASSIF'!$H$24
Name TOTAL2_N: '[1]BILAN PASSIF'!$F$29
Name TOTAL2_N_1: '[1]BILAN PASSIF'!$H$29
Name TOTAL3_N: '[1]BILAN PASSIF'!$F$34
Name TOTAL3_N_1: '[1]BILAN PASSIF'!$H$34
Name TOTAL4_N: '[1]BILAN PASSIF'!$F$54
Name TOTAL4_N_1: '[1]BILAN PASSIF'!$H$54
Name TOTAL5_N: '[1]BILAN PASSIF'!$F$56
Name TOTAL5_N_1: '[1]BILAN PASSIF'!$H$56
Name TOTALGEN_N: '[1]BILAN PASSIF'!$F$58
Name TOTALGEN_N_1: '[1]BILAN PASSIF'!$H$58
Name uniteMonetaire: #REF!
Name uniteMonetaire: #REF!
Name uniteMonetaire: #REF!
Name uniteMonetaire: #REF!

Sheet I Synthèse
D1: #NomClient | Q1: OUI
Q2: NON
A3: IMMOBILISATIONS FINANCIERES
Q4: Faible
Q5: Modéré
A6: Fait par : | B6: BRA | C6: Revu par : | E6: Synthèse du cycle | M6: Date Clôture | N6: XRef | Q6: Elevé
A7: Le : | C7: Le : | M7: #DateClôture | N7: I | Q7: PB
Q8: PE
A9: Risque d'anomalies significatives | D9: Faible | F9: Seuil d'investigation | L9: Niveau de diligences | N9: PB | Q9: PE + VP
A11: Xref | C11: Contrôles | M11: Diligences à tester | N11: Liens
A12: I850 | C12: ='I850 Titres et créances ratta'!E6 -> Analyse de la détention et de la dépréciation des titres et créances rattachées | M12: OUI | N12: I850 Titres financiers
C13: ='I900 Autres immos fi.'!E6 -> Revue des autres immobilisations financières | M13: NON | N13: I900 Autres immos fi.
A16: Revue analytique
A17: cf. Ifi0
A27: CONCLUSION

Sheet I850 Titres et créances ratta
D1: ='I Synthèse'!D1 -> #NomClient | R1: Oui
R2: Non
A3: ='I Synthèse'!A3:O5 -> IMMOBILISATIONS FINANCIERES
R4: Faible
R5: Modéré
A6: Fait par : | B6: ='I Synthèse'!B6 -> BRA | C6: Revu par : | D6: ='I Synthèse'!D6 -> 0 | E6: Analyse de la détention et de la dépréciation des titres et créances rattachées | M6: Date Clôture | O6: XRef | R6: Elevé
A7: Le : | B7: ='I Synthèse'!B7 -> 0 | C7: Le : | D7: ='I Synthèse'!D7 -> 0 | M7: ='I Synthèse'!M7:M7 -> #DateClôture | O7: I850 | R7: PB
O8: I Synthèse | R8: PE
A9: Risque d'anomalies significatives | D9: ='I Synthèse'!D9:E9 -> Faible | F9: Seuil d'investigation | J9: ='I Synthèse'!J9:K9 -> 0 | L9: Niveau de diligences | O9: ='I Synthèse'!N9 -> PB | R9: PE + VP
A11: Objectif Contrôler l'évaluation des titres de participation et des créances rattachées S'assurer de l''exhaustivité de la dépréciation comptabilisée Travail effectué Evaluation des titres de participation et des créances rattachées et / ou CC Actif, par examen de la dernière clôture / situation des filiales et par comparaison de la Quote-Part de l'actif net détenu avec la valeur brute des Titres de Participation et des créances rattachées Remonter en synthèse les dotations / reprises devant être retraitées au niveau du résultat fiscal
A13: Conclusion sur le contrôle
A17: 1° Variation des immobilisations financières
A19: Société | C19: Titres détenus à la clôture N-1 | D19: acquisitions | E19: cessions | F19: Titres détenus à la clôture N | G19: Prix cession | H19: Reprise dépréciation | I19: Plus/moins values constatées | J19: X-Ref | K19: Commentaires
F20: =C20+D20-E20 -> 0 | I20: =G20-E20+H20 -> 0
F21: =C21+D21-E21 -> 0 | I21: =G21-E21+H21 -> 0
F22: =C22+D22-E22 -> 0 | I22: =G22-E22+H22 -> 0
F23: =C23+D23-E23 -> 0 | I23: =G23-E23+H23 -> 0
F24: =C24+D24-E24 -> 0 | I24: =G24-E24+H24 -> 0
F25: =C25+D25-E25 -> 0 | I25: =G25-E25+H25 -> 0
A26: TOTAL | C26: =SUM(C20:C25) -> 0 | D26: =SUM(D20:D25) -> 0 | E26: =SUM(E20:E25) -> 0 | F26: =C26+D26-E26 -> 0 | I26: =SUM(I20:I25) -> 0
A29: Société | C29: Créances rattachées à la clôture N-1 | D29: Augmentation | E29: Diminution | F29: Créances rattachées brutes à la clôture N | G29: Dotation de dépréciation | H29: Reprise de dépréciation | I29: Créances rattachées nettes à la clôture N | J29: X-Ref | K29: Commentaires
A30: =A20 -> 0 | F30: =C30+D30-E30 -> 0 | I30: =F30+G30-H30 -> 0
A31: =A21 -> 0 | F31: =C31+D31-E31 -> 0 | I31: =F31+G31-H31 -> 0
A32: =A22 -> 0 | F32: =C32+D32-E32 -> 0 | I32: =F32+G32-H32 -> 0
A33: =A23 -> 0 | F33: =C33+D33-E33 -> 0 | I33: =F33+G33-H33 -> 0
A34: =A24 -> 0 | F34: =C34+D34-E34 -> 0 | I34: =F34+G34-H34 -> 0
A35: =A25 -> 0 | F35: =C35+D35-E35 -> 0 | I35: =F35+G35-H35 -> 0
A36: TOTAL | C36: =SUM(C30:C35) -> 0 | D36: =SUM(D30:D35) -> 0 | E36: =SUM(E30:E35) -> 0 | F36: =C36+D36-E36 -> 0
A40: 2° Valorisation des immobilisations financières
A42: Société | C42: Valeur brute des titres | D42: % Dét. | E42: Capitaux propres | F42: X-Ref | G42: Quôte part de détention | H42: Plus/moins values latentes | I42: Dépréciation comptabilisée | J42: Dépréciation complémentaire | K42: Commentaires
A43: =A20 -> 0 | H43: =G43-C43 -> 0 | J43: =IF(H43<0,C43-G43-I43,0) -> 0
A44: =A21 -> 0 | C44: =F21 -> 0 | G44: =D44*E44 -> 0 | H44: =G44-C44 -> 0 | J44: =IF(H44<0,C44-G44-I44,0) -> 0
A45: =A22 -> 0 | C45: =F22 -> 0 | G45: =D45*E45 -> 0 | H45: =G45-C45 -> 0 | J45: =IF(H45<0,C45-G45-I45,0) -> 0
A46: =A23 -> 0 | C46: =F23 -> 0 | G46: =D46*E46 -> 0 | H46: =G46-C46 -> 0 | J46: =IF(H46<0,C46-G46-I46,0) -> 0
A47: =A24 -> 0 | C47: =F24 -> 0 | G47: =D47*E47 -> 0 | H47: =G47-C47 -> 0 | J47: =IF(H47<0,C47-G47-I47,0) -> 0
A48: =A25 -> 0 | C48: =F25 -> 0 | G48: =D48*E48 -> 0 | H48: =G48-C48 -> 0 | J48: =IF(H48<0,C48-G48-I48,0) -> 0
A49: TOTAL | C49: =SUM(C43:C48) -> 0 | E49: =SUM(E43:E48) -> 0 | G49: =SUM(G43:G48) -> 0 | H49: =SUM(H43:H48) -> 0 | I49: =SUM(I43:I48) -> 0 | J49: =SUM(J43:J48) -> 0

Sheet I900 Autres immos fi.
D1: ='I Synthèse'!D1 -> #NomClient | R1: Oui
R2: Non
A3: ='I Synthèse'!A3:O5 -> IMMOBILISATIONS FINANCIERES
R4: Faible
R5: Modéré
A6: Fait par : | B6: ='I Synthèse'!B6 -> BRA | C6: Revu par : | D6: ='I Synthèse'!D6 -> 0 | E6: Revue des autres immobilisations financières | M6: Date Clôture | O6: XRef | R6: Elevé
A7: Le : | B7: ='I Synthèse'!B7 -> 0 | C7: Le : | D7: ='I Synthèse'!D7 -> 0 | M7: ='I Synthèse'!M7:M7 -> #DateClôture | O7: I900 | R7: PB
O8: I Synthèse | R8: PE
A9: Risque d'anomalies significatives | D9: ='I Synthèse'!D9:E9 -> Faible | F9: Seuil d'investigation | J9: ='I Synthèse'!J9:K9 -> 0 | L9: Niveau de diligences | O9: ='I Synthèse'!N9 -> PB | R9: PE + VP
A11: Objectif S'assurer de la réalité et la valorisation des autres immobilisations financière à la clôture Travail effectué Obtenir le détail des mouvements des autres immobilisations financières (dépôts et cautionnement versés, etc…) Obtenir les documents justificatifs pour les principales variations
A13: Conclusion sur le contrôle
