Workbook
Name ça: "$#REF !.$B$508:$R$508"
Name CA_N: [1]SIG!$B$8
Name CA_N_1: [1]SIG!$D$8
Name çb: "$#REF !.$A$48:$K$48"
Name çi: "$#REF !.$R$11:$R$508"
Name cloture: "$#REF !.$G$9"
Name çp: "$#REF !.$B$44:$F$44"
Name çr: "$#REF !.$B$62:$H$62"
Name çs: "$#REF !.$B$161:$L$161"
Name dateCloture: #REF!
Name dateCloture: #REF!
Name dateCloture: #REF!
Name dateCloture: #REF!
Name DatesCloture: "$#REF !.$F$9:$#REF !.$M$9"
Name Diligences: 'C100 Variation des CP'!#REF!
Name Diligences: 'C200 Revue de l''actionnariat'!#REF!
Name Diligences: 'C300 Subventions d''équipement'!#REF!
Name Diligences: 'C Synthèse'!$Q$7:$Q$9
Name Etat: 'C100 Variation des CP'!#REF!
Name Etat: 'C200 Revue de l''actionnariat'!#REF!
Name Etat: 'C300 Subventions d''équipement'!#REF!
Name Etat: 'C Synthèse'!$Q$1:$Q$3
Name NomDossier: "$#REF !.$E$1"
Name RAS: 'C100 Variation des CP'!#REF!
Name RAS: 'C200 Revue de l''actionnariat'!#REF!
Name RAS: 'C300 Subventions d''équipement'!#REF!
Name RAS: 'C Synthèse'!$Q$4:$Q$6
Name referenceDossier: #REF!
Name referenceDossier: #REF!
Name referenceDossier: #REF!
Name referenceDossier: #REF!
Name sold6037: "$#REF !.$A$85:$I$85"
Name sold607: "$#REF !.$A$84:$I$84"
Name sold701: "$#REF !.$A$73:$I$73"
Name sold706: "$#REF !.$A$74:$I$74"
Name sold707: "$#REF !.$A$72:$I$72"
Name sold71: "$#REF !.$A$75:$I$75"
Name sold781: "$#REF !.$A$151:$I$151"
Name sold791: "$#REF !.$A$82:$I$82"
Name soldesCapitaux: "$#REF !.$A$55:$J$66"
Name start_toc: #REF!
Name start_toc: #REF!
Name start_toc: #REF!
Name start_toc: #REF!
Name TOTAL1_N: '[1]BILAN PASSIF'!$F$24
Name TOTAL1_N_1: '[1]BILAN PASSIF'!$H$24
Name TOTAL2_N: '[1]BILAN PASSIF'!$F$29
Name TOTAL2_N_1: '[1]BILAN PASSIF'!$H$29
Name TOTAL3_N: '[1]BILAN PASSIF'!$F$34
Name TOTAL3_N_1: '[1]BILAN PASSIF'!$H$34
Name TOTAL4_N: '[1]BILAN PASSIF'!$F$54
Name TOTAL4_N_1: '[1]BILAN PASSIF'!$H$54
Name TOTAL5_N: '[1]BILAN PASSIF'!$F$56
Name TOTAL5_N_1: '[1]BILAN PASSIF'!$H$56
Name TOTALGEN_N: '[1]BILAN PASSIF'!$F$58
Name TOTALGEN_N_1: '[1]BILAN PASSIF'!$H$58
Name uniteMonetaire: #REF!
Name uniteMonetaire: #REF!
Name uniteMonetaire: #REF!
Name uniteMonetaire: #REF!

Sheet C Synthèse
D1: #NomClient | Q1: OUI
Q2: NON
A3: CAPITAUX PROPRES
Q4: Faible
Q5: Modéré
A6: Fait par : | B6: BRA | C6: Revu par : | E6: Synthèse du cycle | M6: Date Clôture | N6: XRef | Q6: Elevé
A7: Le : | C7: Le : | M7: #DateClôture | N7: C | Q7: PB
Q8: PE
A9: Risque d'anomalies significatives | D9: Faible | F9: Seuil d'investigation | L9: Niveau de diligences | N9: PB | Q9: PE + VP
A11: Xref | C11: Contrôles | M11: Diligence à tester | N11: Liens
A12: C100 | C12: ='C100 Variation des CP'!E6 -> Variation des capitaux propres | M12: OUI | N12: C100 Variation des CP
C13: ='C200 Revue de l''actionnariat'!E6 -> Revue de l'actionnariat | M13: NON | N13: C200 Revue de l''actionnariat
C14: ='C300 Subventions d''équipement'!E6 -> Revue des subventions d'équipements | M14: NON | N14: C300 Subventions d''équipement
A17: Revue analytique
A18: Cf. C0
A24: CONCLUSION

Sheet C100 Variation des CP
D1: =+'C Synthèse'!D1:M2 -> #NomClient
A3: CAPITAUX PROPRES
A6: Fait par : | B6: =+'C Synthèse'!B6 -> BRA | C6: Revu par : | D6: =+'C Synthèse'!D6 -> 0 | E6: Variation des capitaux propres | M6: Date Clôture | O6: XRef
A7: Le : | B7: =+'C Synthèse'!B7 -> 0 | C7: Le : | D7: =+'C Synthèse'!D7 -> 0 | M7: =+'C Synthèse'!M7:M7 -> #DateClôture | O7: C100
O8: C Synthèse
A9: Risque d'anomalies significatives | D9: ='C Synthèse'!D9:E9 -> Faible | F9: Seuil d'investigation | J9: ='C Synthèse'!J9:K9 -> 0 | L9: Niveau de diligences | O9: ='C Synthèse'!N9 -> PB
A11: Objectif Evaluation et exhaustivité des capitaux propres Travail effectué Etablir le tableau de variation des capitaux propres, et à partir de ce tableau : - Obtenir les PV d'AG et d'affectation du résultat - Vérifier que l'affectation du résultat comptabilisée est conforme au PV d'AG - Vérifier que la réserve légale est dotée à hauteur de 5% du résultat, plafonnée à 10% du capital social - Vérifier que la situation nette est > à la 1/2 du capital social (si ce n'est pas le cas, penser à convoquer une AGE dans les 4 mois suivant l'approbation des comptes
A13: Conclusion sur le contrôle
A14: Conclure sur les points énoncés ci-dessus
C16: N° Compte | D16: Libellé | F16: Montant début exercice N | G16: Affectation résultat N-1 | H16: Autres mouvements | I16: Résultat N | J16: Montant fin exercice N
B17: A reprendre depuis la FM C0 | J17: =SUM(F17:I17) -> 0
J18: =SUM(F18:I18) -> 0
J19: =SUM(F19:I19) -> 0
J20: =SUM(F20:I20) -> 0
J21: =SUM(F21:I21) -> 0
C22: 120000 | D22: Résultat | J22: =SUM(F22:I22) -> 0
D23: Total capitaux propres | F23: =SUM(F17:F22) -> 0 | G23: =SUM(G17:G22) -> 0 | H23: =SUM(H17:H22) -> 0 | J23: =SUM(J17:J22) -> 0
G25: Dividendes versés
G27: Mise en paiement des dividendes
G28: #Date
G29: #Date
G30: #Date
I31: =SUM(I28:I30) -> 0

Sheet C200 Revue de l'actionnariat
D1: =+'C Synthèse'!D1:M2 -> #NomClient
A3: CAPITAUX PROPRES
A6: Fait par : | B6: =+'C Synthèse'!B6 -> BRA | C6: Revu par : | D6: =+'C Synthèse'!D6 -> 0 | E6: Revue de l'actionnariat | M6: Date Clôture | O6: XRef
A7: Le : | B7: =+'C Synthèse'!B7 -> 0 | C7: Le : | D7: =+'C Synthèse'!D7 -> 0 | M7: =+'C Synthèse'!M7:M7 -> #DateClôture | O7: C200
O8: C Synthèse
A9: Risque d'anomalies significatives | D9: ='C Synthèse'!D9:E9 -> Faible | F9: Seuil d'investigation | J9: ='C Synthèse'!J9:K9 -> 0 | L9: Niveau de diligences | O9: ='C Synthèse'!N9 -> PB
A11: Objectif Contrôle de la composition de l'actionnariat Travail effectué 1/ Vérifier la décomposition de l'actionnariat et obtenir le cas échéant les ordres de mouvements en cas d'agrément d'un nouvel actionnaire/associé 2/ Obtenir le PV d'AG d'agrément du nouvel actionnaire/associé
A13: Conclusion sur le contrôle
A14: Conclure sur les points énoncés ci-dessus
F17: Le capital de l'entité s'élève à la somme de
F18: Nombre d'actions
F19: Valeur nominale | G19: =G17/G18 -> #DIV/0!
B21: Associés | D21: Nombre d'actions | E21: Détention | F21: Qualité
E22: =D22/$G$18 -> #DIV/0!
E23: =D23/$G$18 -> #DIV/0!
E24: =D24/$G$18 -> #DIV/0!
E25: =D25/$G$18 -> #DIV/0!
E26: =D26/$G$18 -> #DIV/0!
E27: =D27/$G$18 -> #DIV/0!
E28: =D28/$G$18 -> #DIV/0!
E29: =D29/$G$18 -> #DIV/0!
E30: =D30/$G$18 -> #DIV/0!
E31: =D31/$G$18 -> #DIV/0!
E32: =D32/$G$18 -> #DIV/0!
C33: TOTAL | D33: =SUM(D22:D32) -> 0 | E33: =D33/$G$18 -> #DIV/0!

Sheet C300 Subventions d'équipement
D1: =+'C Synthèse'!D1:M2 -> #NomClient
A3: CAPITAUX PROPRES
A6: Fait par : | B6: =+'C Synthèse'!B6 -> BRA | C6: Revu par : | D6: =+'C Synthèse'!D6 -> 0 | E6: Revue des subventions d'équipements | M6: Date Clôture | O6: XRef
A7: Le : | B7: =+'C Synthèse'!B7 -> 0 | C7: Le : | D7: =+'C Synthèse'!D7 -> 0 | M7: =+'C Synthèse'!M7:M7 -> #DateClôture | O7: C300
E8: , | O8: C Synthèse
A9: Risque d'anomalies significatives | D9: ='C Synthèse'!D9:E9 -> Faible | F9: Seuil d'investigation | J9: ='C Synthèse'!J9:K9 -> 0 | L9: Niveau de diligences | O9: ='C Synthèse'!N9 -> PB
A11: Objectif Contrôle de l'évaluation et de la réalité des subventions d'équipements reçues Travail effectué 1/ Etablir le tableau de variation des subventions d'équipements ou d'investissements bruts, ainsi que celui des amortissements 2/ Obtenir les conventions attributives de subvention et y contrôler les éléments suivants : - Vérifier que la subvention finance un bien d'équipement - Examiner les obligations de chaque partie dans la convention atttibutive de subvention - Vérifier que les nouvelles subventions d'investissement comptabilisées sont conformes aux conventions attributives - Vérifier que les sorties de subventions se justifient (subventions totalement amorties) 3/ Vérifier pour les nouvelles subventions que la durée d'amortissement appliquée est conforme à la durée d'amortissement du bien subventionné.
A13: Conclusion sur le contrôle
A14: Conclure sur les points énoncés ci-dessus
A17: 1a/ Tableaux de variation des subventions brutes :
B19: Libellé de la subvention | C19: Montant brut fin N-1 | D19: Subventions entrées sur N | E19: X-Ref | F19: Subventions sorties sur N | G19: Montant brut fin N
G20: =C20+D20-F20 -> 0
G21: =C21+D21-F21 -> 0
G22: =C22+D22-F22 -> 0
B23: Total subventions | C23: =SUM(C20:C22) -> 0 | D23: =SUM(D20:D22) -> 0 | F23: =SUM(F20:F22) -> 0 | G23: =SUM(G20:G22) -> 0
B25: Règlement des subventions
B26: #Date
B27: #Date
B28: #Date
D29: =SUM(D26:D28) -> 0
A31: 1b/ Tableaux de variation des amortissements :
B33: Libellé de la subvention | C33: Montant amort. fin N-1 | D33: Dotation sur N | E33: X-Ref | F33: Reprise sur N | G33: Montant amort. fin N
G34: =C34+D34-F34 -> 0
G35: =C35+D35-F35 -> 0
G36: =C36+D36-F36 -> 0
B37: Total amortissement des subventions | C37: =SUM(C34:C36) -> 0 | D37: =SUM(D34:D36) -> 0 | F37: =SUM(F34:F36) -> 0 | G37: =SUM(G34:G36) -> 0
A40: 3/ Contrôle de la durée d'amortissement appliquée, pour les nouvelles subventions :
B42: Libellé de la subvention | C42: Montant de la subvention | D42: Montant du bien subventionné | E42: Durée d'amort. du bien (en linéaire) | F42: Amort. théorique | G42: Amort. calculé (en compta) | H42: X-Ref
F43: =C43/E43 -> #DIV/0!
F44: =C44/E44 -> #DIV/0!
F45: =C45/E45 -> #DIV/0!
E47: Total des tests | G47: =SUM(G43:G45) -> 0
E48: Total des dotations de l'exercice | G48: =D37 -> 0
E49: Scope d'audit | G49: =G47/G48 -> #DIV/0!
