Workbook
Name ActifN: '[1]Balance N Vs N-1'!$D$444
Name ActifN_1: '[1]Balance N Vs N-1'!$E$444
Name ça: "$#REF !.$B$508:$R$508"
Name CA_N: [2]SIG!$B$8
Name CA_N_1: [2]SIG!$D$8
Name çb: "$#REF !.$A$48:$K$48"
Name ChiffreAffairesN: '[1]P&L détaillé'!$D$12
Name ChiffreAffairesN_1: '[1]P&L détaillé'!$E$12
Name çi: "$#REF !.$R$11:$R$508"
Name cloture: "$#REF !.$G$9"
Name çp: "$#REF !.$B$44:$F$44"
Name çr: "$#REF !.$B$62:$H$62"
Name çs: "$#REF !.$B$161:$L$161"
Name dateCloture: #REF!
Name dateCloture: #REF!
Name dateCloture: #REF!
Name dateCloture: #REF!
Name dateCloture: #REF!
Name dateCloture: #REF!
Name dateCloture: #REF!
Name dateCloture: #REF!
Name dateCloture: #REF!
Name dateCloture: #REF!
Name dateCloture: #REF!
Name dateCloture: #REF!
Name dateCloture: #REF!
Name DatesCloture: "$#REF !.$F$9:$#REF !.$M$9"
Name Diligences: 'A100 Rappro BA-BG'!#REF!
Name Diligences: 'A110 Revue frs débiteurs'!#REF!
Name Diligences: 'A200 Rappro constructeur'!#REF!
Name Diligences: 'A300 Réciprocité intragroupe'!#REF!
Name Diligences: 'A410 Revue FNP'!#REF!
Name Diligences: 'A420 Revue AAR'!#REF!
Name Diligences: 'A430 Revue Primes const'!#REF!
Name Diligences: 'A440 Revue CCA'!#REF!
Name Diligences: 'A500 Circularisations'!#REF!
Name Diligences: 'A600 Revue AACE'!#REF!
Name Diligences: 'A700 Revue EAP'!#REF!
Name Diligences: Questionnaire!$R$7:$R$9
Name Diligences: #REF!
Name Etat: 'A100 Rappro BA-BG'!#REF!
Name Etat: 'A110 Revue frs débiteurs'!#REF!
Name Etat: 'A200 Rappro constructeur'!#REF!
Name Etat: 'A300 Réciprocité intragroupe'!#REF!
Name Etat: 'A410 Revue FNP'!#REF!
Name Etat: 'A420 Revue AAR'!#REF!
Name Etat: 'A430 Revue Primes const'!#REF!
Name Etat: 'A440 Revue CCA'!#REF!
Name Etat: 'A500 Circularisations'!#REF!
Name Etat: 'A600 Revue AACE'!#REF!
Name Etat: 'A700 Revue EAP'!#REF!
Name Etat: Questionnaire!$R$1:$R$3
Name Etat: #REF!
Name libellé: [3]Feuil5!$A$1:$B$1103
Name NomDossier: "$#REF !.$E$1"
Name RAS: 'A100 Rappro BA-BG'!#REF!
Name RAS: 'A110 Revue frs débiteurs'!#REF!
Name RAS: 'A200 Rappro constructeur'!#REF!
Name RAS: 'A300 Réciprocité intragroupe'!#REF!
Name RAS: 'A410 Revue FNP'!#REF!

Sheet A Synthèse
R1: OUI
R2: NON
A3: FOURNISSEURS - ACHATS
R4: Faible
R5: Modéré
A6: Fait par : | B6: BRA | C6: Revu par : | E6: Synthèse du cycle | M6: Date Clôture | O6: XRef | R6: Elevé
A7: Le : | C7: Le : | M7: 31/12/N | O7: A | R7: PB
R8: PE
A9: Risque d'anomalies significatives | D9: Elevé | F9: Seuil d'investigation | J9: =98*0.15 -> 14.7 | L9: Niveau de diligences | O9: PE | R9: PE + VP
A11: Xref | C11: Contrôles | M11: Diligence à tester | O11: Liens
A12: A100 | C12: Rapprochement BA-BG | M12: OUI | O12: A100 Rappro BA-BG | Q12: P | S12: Ok BG N
A13: A110 | C13: Revue des fournisseurs débiteurs | M13: OUI | O13: A110 Revue frs débiteurs | Q13: f | S13: Ok RG / BG N-1
A14: A200 | C14: Rapprochement constructeur | M14: OUI | O14: A200 Rappro constructeur | Q14: a | S14: Ok Rapppro doc…
A15: A300 | C15: Réciprocité intragroupe | M15: OUI | O15: A300 Réciprocité intragroupe | Q15: E | S15: Ok Rapppro doc…
A16: A410 | C16: Revue des FNP | M16: OUI | O16: A410 Revue FNP | Q16: d | S16: autres
A17: A420 | C17: Revue des AAR | M17: OUI | O17: A420 Revue AAR | Q17: Ʇ | S17: Contrôle arithmétique
A18: A420 | C18: Revue des primes constructeurs | M18: OUI | O18: A430 Revue primes const | Q18: G | S18: Ok Rapppro doc…
A19: A440 | C19: Revue des CCA | M19: OUI | O19: A440 Revue CCA
A20: A500 | C20: Circularisations | M20: OUI | O20: A500 Circularisations
A21: A600 | C21: Revue AACE | M21: OUI | O21: A600 Revue AACE
C22: Revue EAP | M22: NON | O22: A700 Revue EAP
A25: Revue analytique
A26: Cf. A0
A28: CONCLUSION
A29: SATISFAISANT

Sheet Questionnaire
D1: ='A Synthèse'!D1:M2 -> 0 | R1: N/A
R2: A faire
A3: FOURNISSEURS - ACHATS | R3: Terminé
R4: Faible
R5: Modéré
A6: Fait par : | B6: ='A Synthèse'!B6 -> BRA | C6: Revu par : | D6: ='A Synthèse'!D6 -> 0 | E6: Questionnaire | M6: Date Clôture | O6: XRef | R6: Elevé
A7: Le : | B7: ='A Synthèse'!B7 -> 0 | C7: Le : | D7: ='A Synthèse'!D7 -> 0 | M7: ='A Synthèse'!M7:N7 -> 31/12/N | O7: A | R7: PB
O8: A Synthèse | R8: PE
A9: Risque d'anomalies significatives | D9: ='A Synthèse'!D9:E9 -> Elevé | F9: Seuil d'investigation | J9: ='A Synthèse'!J9:K9 -> 14.7 | L9: Niveau de diligences | O9: ='A Synthèse'!O9:P9 -> PE | R9: PE + VP
A11: 1. RISQUES INHERENTS
A12: Question | H12: N/A | I12: OUI | J12: NON | K12: SI NON : Commentaires sur les risques d'anomalies significatives dans les comptes ou la continuité d'exploitation et REF.
A13: Les achats effectués à des sociétés apparentées sont-ils non significatifs ? [R-V]
A14: Le nombre limité de fournisseurs facilite-t-il le suivi ? [E]
A15: Les fournisseurs sont-ils diligents pour émettre leurs factures rapidement ? [E-S]
A16: Autres risques inhérents identifiés :
A18: 2. RISQUES LIES AU CONTRÔLE
A19: Question | H19: N/A | I19: OUI | J19: NON | K19: SI NON : Commentaires sur les risques d'anomalies significatives dans les comptes ou la continuité d'exploitation et REF.
A20: Les commandes font-elles l'objet d'une procédure d'autorisation ? [R]
A21: Existe-t-il des bons de réception pré-numérotés ?[R-S]
A22: Les contrôles qualitatifs et quantitatifs des réceptions font-ils l’objet d’un visa matérialisé par une personne indépendante ? [R]
A23: Lors de la réception des factures, est-il apposé un cachet ORIGINAL sur l'un des exemplaires reçus ? [R]
A24: Les factures sont-elles rapprochées des bons de réception et des bons de commande ? [R-V]
A25: Existe-t-il une procédure de validation et de suivi des avoirs demandés ? [V-E]
A26: Les factures comportent-elles l'imputation comptable ? [I]
A27: Font-elles mention d’une référence de règlement ? [R]
A28: Y figure-t-il un visa de saisie et de paiement ? [R-I]
A29: La comptabilité fournisseurs est-elle à jour ? [E]
A30: Les paiements se font-ils systématiquement au vu d'une pièce justificative ? [R]
A31: Y a-t-il une procédure de collecte des informations permettant de respecter la séparation des exercices (BR en attente, avoirs en attente, factures non reçues, etc, ...) mise en œuvre par le service achats et le service comptable ? [E-S]
... A38: Autres risques liés aux contrôles identifiés :
A42: Préparé par : ……………………………………………. | M42: Signature
A43: Commentaire
A45: APPROBATION DU COMMISSAIRE AUX COMPTES : | M45: Signature
A46: Commentaire

Sheet A100 Rappro BA-BG
D1: ='A Synthèse'!D1:M2 -> 0
A3: FOURNISSEURS - ACHATS
A6: Fait par : | B6: ='A Synthèse'!B6 -> BRA | C6: Revu par : | D6: ='A Synthèse'!D6 -> 0 | E6: Rapprochement BA-BG | M6: Date Clôture | O6: XRef
A7: Le : | B7: ='A Synthèse'!B7 -> 0 | C7: Le : | D7: ='A Synthèse'!D7 -> 0 | M7: ='A Synthèse'!M7:N7 -> 31/12/N | O7: A100
O8: A Synthèse
A9: Risque d'anomalies significatives | D9: ='A Synthèse'!D9:E9 -> Elevé | F9: Seuil d'investigation | J9: ='A Synthèse'!J9:K9 -> 14.7 | L9: Niveau de diligences | O9: ='A Synthèse'!O9:P9 -> PE
A11: Objectif : Contrôle de l'exhaustivité des dettes fournisseurs Contrôle de la correcte présentation des comptes entre clients débiteurs et clients créditeurs. Travail effectué Contrôle de la concordance entre la balance auxiliaire et la balance générale. S'assurer que les fournisseurs débiteurs sont bien identifiés et comptabilisés en fournisseurs débiteurs dans les comptes.
A13: Conclusion sur le contrôle
A14: SATISFAISANT
B17: BALANCE AUXILIAIRE | D17: Solde débiteur | E17: Solde créditeur | F17: Solde Net
B18: 401000 - Fournisseurs | F18: =D18-E18 -> 0 | G18: A101
B21: BALANCE GENERALE | D21: Solde débiteur | E21: Solde créditeur | F21: Solde Net
B22: 401000 - Fournisseurs | D22: =SUM(#REF!) -> #REF! | E22: =SUM(#REF!) -> #REF! | F22: =D22-E22 -> #REF!
B23: 401XX
B24: Total | D24: =+SUM(D22:D23) -> #REF! | E24: =+SUM(E22:E23) -> #REF! | F24: =D24-E24 -> #REF! | G24: X-Ref
B26: Ecart | D26: =D18-D22 -> #REF! | E26: =E18-E22 -> #REF! | F26: =F18-F22 -> #REF!

Sheet A110 Revue frs débiteurs
D1: ='A Synthèse'!D1:M2 -> 0
A3: FOURNISSEURS - ACHATS
A6: Fait par : | B6: ='A Synthèse'!B6 -> BRA | C6: Revu par : | D6: ='A Synthèse'!D6 -> 0 | E6: Revue fournisseurs débiteurs | M6: Date Clôture | O6: XRef
A7: Le : | B7: ='A Synthèse'!B7 -> 0 | C7: Le : | D7: ='A Synthèse'!D7 -> 0 | M7: ='A Synthèse'!M7:N7 -> 31/12/N | O7: A110
O8: A Synthèse
A9: Risque d'anomalies significatives | D9: ='A Synthèse'!D9:E9 -> Elevé | F9: Seuil d'investigation | J9: ='A Synthèse'!J9:K9 -> 14.7 | L9: Niveau de diligences | O9: ='A Synthèse'!O9:P9 -> PE
A11: Objectif Présentation des fournisseurs Travail effectué S’assurer qu’il n’existe pas de fournisseurs débiteurs significatifs compensés avec les fournisseurs créditeurs. Le cas échéant proposer le reclassement. Comprendre pourquoi la société comptabilise des fournisseurs débiteurs et vérifier que ces soldes ne sont pas constitutifs d'une anomalie ou d'un litige.
A13: Conclusion sur le contrôle
A14: SATISFAISANT
E17: Débiteurs | F17: Créditeurs
D18: Balance auxiliaire Frs | E18: ='A100 Rappro BA-BG'!D18 -> 0 | F18: ='A100 Rappro BA-BG'!E18 -> 0
B22: Principaux fournisseurs débiteurs | C22: Solde | D22: % des débiteurs | E22: Analyse | I22: Ajustement | K22: X-Ref
C23: =#REF! -> #REF! | D23: =+C23/$E$18 -> #REF! | I23: N/A
C24: =#REF! -> #REF! | D24: =+C24/$E$18 -> #REF! | I24: N/A
D25: =+C25/$E$18 -> #DIV/0!
A26: Total fournisseurs débiteurs testés | C26: =SUM(C23:C25) -> #REF! | D26: =+C26/$E$18 -> #REF!

Sheet A200 Rappro constructeur
D1: ='A Synthèse'!D1:M2 -> 0
A3: FOURNISSEURS - ACHATS
A6: Fait par : | B6: ='A Synthèse'!B6 -> BRA | C6: Revu par : | D6: ='A Synthèse'!D6 -> 0 | E6: Rapprochement constructeur | M6: Date Clôture | O6: XRef
A7: Le : | B7: ='A Synthèse'!B7 -> 0 | C7: Le : | D7: ='A Synthèse'!D7 -> 0 | M7: ='A Synthèse'!M7:N7 -> 31/12/N | O7: A200
O8: A Synthèse
A9: Risque d'anomalies significatives | D9: ='A Synthèse'!D9:E9 -> Elevé | F9: Seuil d'investigation | J9: ='A Synthèse'!J9:K9 -> 14.7 | L9: Niveau de diligences | O9: ='A Synthèse'!O9:P9 -> PE
A11: Objectif Exhaustivité de la dette constructeur Travail effectué A partir des états transmis issus du logiciel constructeur (Link, DCS,…), rapprochement des soldes avec ceux issus de la comptabilité.
A13: Conclusion sur le contrôle
A14: SATISFAISANT
A17: VEHICULES OCCASION | D17: VEHICULES NEUFS | G17: PIECES DE RECHANGE
A18: Compta RENAULT | D18: =+A18 -> Compta RENAULT | G18: =A18 -> Compta RENAULT
A19: Compte 1100 VO | B19: =-#REF! -> #REF! | D19: Compte 1111 VN | G19: Compte 1100 VO | H19: =-#REF! -> #REF!
A23: Total Compta CITROEN | B23: =SUM(B19:B22) -> #REF! | D23: =+A23 -> Total Compta CITROEN | E23: =SUM(E19:E22) -> 0 | G23: Total Compta CITROEN | H23: =SUM(H19:H22) -> #REF!
A24: Relevé COGERA de 31-12-N | D24: =A24 -> Relevé COGERA de 31-12-N | G24: =+A24 -> Relevé COGERA de 31-12-N
A26: Encours Financement VO | G26: Encours Financement VO
B32: =SUM(B25:B31) -> 0 | E32: =SUM(E25:E31) -> 0 | H32: =SUM(H25:H31) -> 0
A34: Ecart VO | B34: =+B23-B32 -> #REF! | D34: Ecart VN | E34: =E23-E32 -> 0 | G34: Ecart VO | H34: =+H23-H32 -> #REF!

Sheet A300 Réciprocité intragroupe
D1: ='A Synthèse'!D1:M2 -> 0
A3: FOURNISSEURS - ACHATS
A6: Fait par : | B6: ='A Synthèse'!B6 -> BRA | C6: Revu par : | D6: ='A Synthèse'!D6 -> 0 | E6: Réciprocité intragroupe | M6: Date Clôture | O6: XRef
A7: Le : | B7: ='A Synthèse'!B7 -> 0 | C7: Le : | D7: ='A Synthèse'!D7 -> 0 | M7: ='A Synthèse'!M7:N7 -> 31/12/N | O7: A300
O8: A Synthèse
A9: Risque d'anomalies significatives | D9: ='A Synthèse'!D9:E9 -> Elevé | F9: Seuil d'investigation | J9: ='A Synthèse'!J9:K9 -> 14.7 | L9: Niveau de diligences | O9: ='A Synthèse'!O9:P9 -> PE
A11: Objectif Contrôler l'exhaustivité des soldes frs interco Travail effectué A partir des soldes interco, contrôler la réciprocité des encours avec ceux de la balance frs de ces mêmes sociétés.
A13: Conclusion sur le contrôle
F17: Solde chez X | I17: Solde chez intercos | L17: Ecart
F18: débit | G18: X-Ref BA | H18: crédit | I18: débit | J18: crédit | K18: X-Ref BA
E19: A | L19: =F19-J19 -> 0
E20: B | L20: =F20-J20 -> 0
E21: C | L21: =F21-J21 -> 0
E22: D | L22: =F22-J22 -> 0

Sheet A410 Revue FNP
D1: ='A Synthèse'!D1:M2 -> 0
A3: FOURNISSEURS - ACHATS
A6: Fait par : | B6: ='A Synthèse'!B6 -> BRA | C6: Revu par : | D6: ='A Synthèse'!D6 -> 0 | E6: Revue FNP | M6: Date Clôture | O6: XRef
A7: Le : | B7: ='A Synthèse'!B7 -> 0 | C7: Le : | D7: ='A Synthèse'!D7 -> 0 | M7: ='A Synthèse'!M7:N7 -> 31/12/N | O7: A410
O8: A Synthèse
A9: Risque d'anomalies significatives | D9: ='A Synthèse'!D9:E9 -> Elevé | F9: Seuil d'investigation | J9: ='A Synthèse'!J9:K9 -> 14.7 | L9: Niveau de diligences | O9: ='A Synthèse'!O9:P9 -> PE
A11: Objectif Exhaustivité et évaluation des FNP Travail effectué Obtenir les détails des comptes de FNP et les cadrer avec la balance générale et effectuer les contrôles arithmétiques nécessaires. Procéder par revue analytique : identifier les principales FNP et identifier si ce sont des éléments récurrents notamment des frais généraux (à partir des détails N-1). Investiguer notamment en cas d'absence de FNP que l'on sait de nature récurrente. Selon l'approche d'audit retenue sur le dossier (en lien notamment avec l'assurance que l'on a sur le process Frs/Achats et les autres tests de détail menés sur les fournisseurs notamment le cut off), cette revue analytique peut être suffisante pour valider l'exhaustivité et l'exactitude des FNP. Pour les FNP > SI, obtenir les justificatifs : factures émises sur la période subséquente et si nécessaires bons de livraisons / réalisation des prestations… Croiser ce test avec les travaux réalisés sur le cut off et les circularisations frs notamment.
A13: Conclusion sur le contrôle
A14: SATISFAISANT
A17: a) Revue analytique des FNP : | C17: X-ref détail des FNP | D17: A411
C19: Nature des FNP | D19: 31/12/N | E19: 31/12/N-1 | F19: Var | G19: Var % | H19: Caractère récurrent | I19: Ref pièce | J19: Analyse
C30: TOTAL | D30: =SUM(D20:D29) -> 0 | E30: =SUM(E20:E29) -> 0 | F30: =SUM(F22:F29) -> 0 | G30: =+F30/E30 -> #DIV/0!
C31: TOTAL COMPTA | D31: =(#REF!+#REF!+#REF!)/1000 -> #REF! | E31: =(#REF!+#REF!+#REF!)/1000 -> #REF! | F31: =D31-E31 -> #REF! | G31: =+F31/E31 -> #REF!

Sheet A420 Revue AAR
D1: ='A Synthèse'!D1:M2 -> 0
A3: FOURNISSEURS - ACHATS
A6: Fait par : | B6: ='A Synthèse'!B6 -> BRA | C6: Revu par : | D6: ='A Synthèse'!D6 -> 0 | E6: Revue AAR | M6: Date Clôture | O6: XRef
A7: Le : | B7: ='A Synthèse'!B7 -> 0 | C7: Le : | D7: ='A Synthèse'!D7 -> 0 | M7: ='A Synthèse'!M7:N7 -> 31/12/N | O7: A420
O8: A Synthèse
A9: Risque d'anomalies significatives | D9: ='A Synthèse'!D9:E9 -> Elevé | F9: Seuil d'investigation | J9: ='A Synthèse'!J9:K9 -> 14.7 | L9: Niveau de diligences | O9: ='A Synthèse'!O9:P9 -> PE
A11: Objectif Réalité et évaluation des AAR Travail effectué Obtenir les détails des comptes de AAR et les cadrer avec la balance générale et effectuer les contrôles arithmétiques nécessaires. Procéder par revue analytique : identifier les principaux AAR et identifier si ce sont des éléments récurrents (à partir des détails N-1), la nature des AAR (avoirs sur factures, RFA,...). Investiguer notamment en cas d'absence d'AAR que l'on sait de nature récurrente. Selon l'approche d'audit retenue sur le dossier (en lien notamment avec l'assurance que l'on a sur le process Frs/Achats et les autres tests de détail menés sur les frs notamment le cut off), cette revue analytique peut être suffisante pour contrôler la réalité et l'exactitude des AAR. Pour les AAR > SI, obtenir les justificatifs : avoirs émis sur la période subséquente A partir du journal d'achat de janvier N+1 sélection des avoirs HT > à SI et contrôle de la nécessité de provisionner un AAR à la clôture.
A13: Conclusion sur le contrôle
A14: SATISFAISANT
A17: a) Revue analytique des AAR :
C19: Principaux AAR | D19: 31/12/N | E19: 31/12/N-1 | F19: Var | G19: Var % | H19: Caractère récurrent | I19: Ref pièce | J19: Analyse | Q19: Dénouement N-1
Q21: 1
Q23: 1
Q25: 1
Q28: 0.9999
Q29: 1
C35: TOTAL | D35: =SUM(D20:D34) -> 0 | E35: =SUM(E20:E34) -> 0 | F35: =SUM(F20:F34) -> 0 | G35: =+F35/E35 -> #DIV/0!
D36: S0 | E36: S0
C37: TOTAL COMPTA
D40: Taux de dénouement | F40: =(D23+D25+D28-36000+D32+D33+#REF!+#REF!)/D35 -> #REF!

Sheet A430 Revue Primes const
D1: ='A Synthèse'!D1:M2 -> 0
A3: FOURNISSEURS - ACHATS
A6: Fait par : | B6: ='A Synthèse'!B6 -> BRA | C6: Revu par : | D6: ='A Synthèse'!D6 -> 0 | E6: Revue Primes constructeurs | M6: Date Clôture | O6: XRef
A7: Le : | B7: ='A Synthèse'!B7 -> 0 | C7: Le : | D7: ='A Synthèse'!D7 -> 0 | M7: ='A Synthèse'!M7:N7 -> 31/12/N | O7: A430
O8: A Synthèse
A9: Risque d'anomalies significatives | D9: ='A Synthèse'!D9:E9 -> Elevé | F9: Seuil d'investigation | J9: ='A Synthèse'!J9:K9 -> 14.7 | L9: Niveau de diligences | O9: ='A Synthèse'!O9:P9 -> PE
A11: Objectif Réalité et évaluation des primes constructeurs Travail effectué 1/ Recensement des primes constructeurs perçues en N-1 et entretien avec le RAf pour identifier les évolutions en matière d'attribution de primes, les nouvelles primes versées sur l'exercice,... Si oui, s'assurer qu'elle comptabilise/provisionne bien ces RFA à la clôture de l'exercice audité. 2/ Revue analytique des primes N/N-1 3/ Pprocéder à des test de détail sur les RFA. S'assurer que les taux utilisés sont conformes aux contrats (s'il y en a) ou autre élément de preuve (mails, entretien avec la Direction, …) ou fichiers issus du logiciel constructeur S'assurer en outre que la base de CA annuel utilisée pour calculer ces primes est conforme au CA réalisé en stat commerciale. 4/ Dans tous les cas, vérifier sur N l'apurement des primes comptabilisées en N et en N-1, permettant de contrôler la méthode et les sous-provisions éventuelles.
A13: Conclusion sur le contrôle
A17: FOURNISSEURS | B17: NATURE | C17: MONTANT TTC | D17: MONTANT N-1 | E17: VARIATION | F17: REF | G17: Dénouement Provision N sur N+1 | H17: Rappel Dénouement Provision N-1 sur N
E19: =C19-D19 -> 0
E20: =C20-D20 -> 0
E21: =C21-D21 -> 0
E22: =C22-D22 -> 0
E23: =C23-D23 -> 0
E24: =C24-D24 -> 0
E25: =C25-D25 -> 0
E26: =C26-D26 -> 0
E27: =C27-D27 -> 0
E28: =C28-D28 -> 0
E29: =C29-D29 -> 0
E30: =C30-D30 -> 0
E31: =C31-D31 -> 0
B33: TOTAL SOLDES ANALYSES | C33: =SUM(C19:C31) -> 0 | D33: =SUM(D19:D31) -> 0 | E33: =SUM(E19:E31) -> 0
B34: TOTAL AAR FOURNISSEURS | E34: =+C34-D34 -> 0
B35: Scope | C35: =C33/C34 -> #DIV/0! | D35: =D33/D34 -> #DIV/0! | E35: =E33/E34 -> #DIV/0!
B36: TOTAL DENOUEMENT AAR au
B37: soit | C37: =C36/C34 -> #DIV/0! | D37: des AAR

Sheet A440 Revue CCA
D1: ='A Synthèse'!D1:M2 -> 0
A3: FOURNISSEURS - ACHATS
A6: Fait par : | B6: ='A Synthèse'!B6 -> BRA | C6: Revu par : | D6: ='A Synthèse'!D6 -> 0 | E6: Revue CCA | M6: Date Clôture | O6: XRef
A7: Le : | B7: ='A Synthèse'!B7 -> 0 | C7: Le : | D7: ='A Synthèse'!D7 -> 0 | M7: ='A Synthèse'!M7:N7 -> 31/12/N | O7: A440
O8: A Synthèse
A9: Risque d'anomalies significatives | D9: ='A Synthèse'!D9:E9 -> Elevé | F9: Seuil d'investigation | J9: ='A Synthèse'!J9:K9 -> 14.7 | L9: Niveau de diligences | O9: ='A Synthèse'!O9:P9 -> PE
A11: Objectif Exhaustivité et évaluation des charges constatées d'avance Travail effectué Obtenir le détail des CCA et le rapprocher de la comptabilité Effectuer des tests justifiant la correcte évaluation des CCA provisionnés Effectuer un comparatif par grandes masses avec les CCA de l'exercice précédent et expliquer les principales évolutions
A13: Conclusion sur le contrôle
A14: SATISFAISANT
A17: a) Revue analytique des CCA :
B19: Nature des FNP | C19: 31/12/N | D19: 31/12/N-1 | E19: Var | F19: Var % | G19: Caractère récurrent | H19: Ref pièce | I19: Analyse
B20: Location | E20: =C20-D20 -> 0 | F20: =E20/D20 -> #DIV/0!
B21: Entretien et maintenance | E21: =C21-D21 -> 0 | F21: =E21/D21 -> #DIV/0!
B22: Assurance | E22: =C22-D22 -> 0 | F22: =E22/D22 -> #DIV/0!
B23: Honoraires | E23: =C23-D23 -> 0 | F23: =E23/D23 -> #DIV/0!
B24: Déplacements, missions | E24: =C24-D24 -> 0 | F24: =E24/D24 -> #DIV/0!
B25: Intérim | E25: =C25-D25 -> 0 | F25: =E25/D25 -> #DIV/0!
B26: XXX | E26: =C26-D26 -> 0 | F26: =E26/D26 -> #DIV/0!
B27: TOTAL | C27: =SUM(C20:C26) -> 0 | D27: =SUM(D20:D26) -> 0 | E27: =SUM(E20:E26) -> 0 | F27: =+E27/D27 -> #DIV/0!
A29: b) Test de détail sur les CCA :
B31: Frs | C31: N° facture | D31: Date facturation | E31: Montant HT | F31: Date de la prestation ou réception | G31: N° BL | H31: Ref pièce | I31: Observations
C34: Population testée | E34: =SUM(E32:E33) -> 0
C35: Population totale
C36: % Testé | E36: =E34/E35 -> #DIV/0!

Sheet A500 Circularisations
D1: ='A Synthèse'!D1:M2 -> 0
A3: FOURNISSEURS - ACHATS
A6: Fait par : | B6: ='A Synthèse'!B6 -> BRA | C6: Revu par : | D6: ='A Synthèse'!D6 -> 0 | E6: Circularisations | M6: Date Clôture | O6: XRef
A7: Le : | B7: ='A Synthèse'!B7 -> 0 | C7: Le : | D7: ='A Synthèse'!D7 -> 0 | M7: ='A Synthèse'!M7:N7 -> 31/12/N | O7: A500
O8: A Synthèse
A9: Risque d'anomalies significatives | D9: ='A Synthèse'!D9:E9 -> Elevé | F9: Seuil d'investigation | J9: ='A Synthèse'!J9:K9 -> 14.7 | L9: Niveau de diligences | O9: ='A Synthèse'!O9:P9 -> PE
A11: Objectif Exhaustivité des encours frs par circularisation des tiers Travail effectué 1/ A partir de la balance auxiliaire provisioire en date du 31-12-N, sélectionner les mouvements créditeurs les plus significatifs (cf. procédure circularisations dans Sharepoint) 2/ Emettre des courriers de demande de confirmation de soldes 3/ Exploiter les réponses de circularisations reçues 4/ En cas de non réponse, cf. revue décaissements post-clôture
A13: Conclusion sur le contrôle
A17: 1° Critères de sélections
A19: cf. fichier sélection auto circul
A23: 2° Tableau de synthèse des circularisations
F25: Comptabilité | G25: Justification du solde | K25: Justification du solde des mouvements créditeurs
A26: N° de compte | B26: Nom du fournisseur | C26: Date envoi | D26: Date relance | E26: Date réponse | F26: Solde Frs à la clôture (BA) | G26: Solde confirmé par le tiers | H26: Ecart | I26: Ecart justifié | J26: Ecart non justifié | K26: Total mvt créditeur à la clôture | L26: Total des mvt confirmé | M26: Ecart | N26: Ecart justifié | O26: Ecart non justifié | P26: Analyse
H27: =F27-G27 -> 0 | J27: =H27-I27 -> 0 | M27: =K27-L27 -> 0 | O27: =M27-N27 -> 0
H28: =F28-G28 -> 0 | J28: =H28-I28 -> 0 | M28: =K28-L28 -> 0 | O28: =M28-N28 -> 0
H29: =F29-G29 -> 0 | J29: =H29-I29 -> 0 | M29: =K29-L29 -> 0 | O29: =M29-N29 -> 0
H30: =F30-G30 -> 0 | J30: =H30-I30 -> 0 | M30: =K30-L30 -> 0 | O30: =M30-N30 -> 0
H31: =F31-G31 -> 0 | J31: =H31-I31 -> 0 | M31: =K31-L31 -> 0 | O31: =M31-N31 -> 0
H32: =F32-G32 -> 0 | J32: =H32-I32 -> 0 | M32: =K32-L32 -> 0 | O32: =M32-N32 -> 0
C34: Total sélection solde créditeurs = | F34: =SUM(F27:F32) -> 0 | H34: Total sélection mvt créditeurs = | K34: =SUM(K27:K32) -> 0
C36: Total balance solde créditeurs = | H36: Total balance mvt créditeurs =
C38: % sélection solde créditeurs = | F38: =F34/F36 -> #DIV/0! | H38: % sélection mvt créditeurs = | K38: =K34/K36 -> #DIV/0!

Sheet A600 Revue AACE
D1: ='A Synthèse'!D1:M2 -> 0
A3: FOURNISSEURS - ACHATS
A6: Fait par : | B6: ='A Synthèse'!B6 -> BRA | C6: Revu par : | D6: ='A Synthèse'!D6 -> 0 | E6: Revue AACE | M6: Date Clôture | O6: XRef
A7: Le : | B7: ='A Synthèse'!B7 -> 0 | C7: Le : | D7: ='A Synthèse'!D7 -> 0 | M7: ='A Synthèse'!M7:N7 -> 31/12/N | O7: A600
O8: A Synthèse
A9: Risque d'anomalies significatives | D9: ='A Synthèse'!D9:E9 -> Elevé | F9: Seuil d'investigation | J9: ='A Synthèse'!J9:K9 -> 14.7 | L9: Niveau de diligences | O9: ='A Synthèse'!O9:P9 -> PE
A11: Objectif Exhaustivité et évaluation des autres charges externes Travail effectué Revue analytique des charges : comprendre les variations par grands postes de charges S'assurer que la variation est cohérante avec l'analyse de l'activité, éventuellement au moyen de ratios pertinents (commissions / ventes ou achats, frais de ports / CA, énergie / activité…) En cas d'honoraires significatifs, contrôler la DADS2 Conventions réglementées : être vigilant sur les conventions réglementées et les nouvelles opérations entre sociétés liées qui peuvent être relevées lors de ces travaux. Prendre en copie les éléments nécessaires pour le rapport sur les conventions réglementées.
A13: Conclusion sur le contrôle
A14: SATISFAISANT
C17: CA de l'exercice
B19: Libellé | C19: N | D19: % des AACE | E19: % du CA | F19: N-1 | G19: Variation K€ / % | I19: Commentaire | O19: X-Ref
B20: Achats non stocks de matière et fournitures | D20: =C20/C36 -> #DIV/0! | E20: =C20/$D$17 -> #DIV/0! | G20: =C20-F20 -> 0 | H20: =+G20/F20 -> #DIV/0!
B21: Locations | D21: =C21/D37 -> #DIV/0! | E21: =C21/$D$17 -> #DIV/0! | G21: =C21-F21 -> 0 | H21: =+G21/F21 -> #DIV/0!
B22: Entretien et réparations | D22: =C22/D38 -> #DIV/0! | E22: =C22/$D$17 -> #DIV/0! | G22: =C22-F22 -> 0 | H22: =+G22/F22 -> #DIV/0!
B23: Primes d'assurances | D23: =C23/D39 -> #DIV/0! | E23: =C23/$D$17 -> #DIV/0! | G23: =C23-F23 -> 0 | H23: =+G23/F23 -> #DIV/0!
B24: Etudes et recherches | D24: =C24/D40 -> #DIV/0! | E24: =C24/$D$17 -> #DIV/0! | G24: =C24-F24 -> 0 | H24: =+G24/F24 -> #DIV/0!
B25: Divers services extérieurs | D25: =C25/D41 -> #DIV/0! | E25: =C25/$D$17 -> #DIV/0! | G25: =C25-F25 -> 0 | H25: =+G25/F25 -> #DIV/0!
B26: Personnel extérieur à l'entreprise | D26: =C26/D42 -> #DIV/0! | E26: =C26/$D$17 -> #DIV/0! | G26: =C26-F26 -> 0 | H26: =+G26/F26 -> #DIV/0!
B27: Rémunérations d'intermédiaires et honoraires | D27: =C27/D43 -> #DIV/0! | E27: =C27/$D$17 -> #DIV/0! | G27: =C27-F27 -> 0 | H27: =+G27/F27 -> #DIV/0!
B28: Publicité, publications, relations publiques | D28: =C28/D44 -> #DIV/0! | E28: =C28/$D$17 -> #DIV/0! | G28: =C28-F28 -> 0 | H28: =+G28/F28 -> #DIV/0!
B29: Transports de biens et transports collectifs du personnel | D29: =C29/D45 -> #DIV/0! | E29: =C29/$D$17 -> #DIV/0! | G29: =C29-F29 -> 0 | H29: =+G29/F29 -> #DIV/0!
B30: Déplacements, missions et réceptions | D30: =C30/D46 -> #DIV/0! | E30: =C30/$D$17 -> #DIV/0! | G30: =C30-F30 -> 0 | H30: =+G30/F30 -> #DIV/0!
B31: Frais postaux et de télécommunications | D31: =C31/D47 -> #DIV/0! | E31: =C31/$D$17 -> #DIV/0! | G31: =C31-F31 -> 0 | H31: =+G31/F31 -> #DIV/0!
B32: Divers autres services extérieurs | D32: =C32/D48 -> #DIV/0! | E32: =C32/$D$17 -> #DIV/0! | G32: =C32-F32 -> 0 | H32: =+G32/F32 -> #DIV/0!
... B34: Autres charges | D34: =C34/D50 -> #DIV/0! | E34: =C34/$D$17 -> #DIV/0! | G34: =C34-F34 -> 0 | H34: =+G34/F34 -> #DIV/0!
B36: TOTAL AACE | C36: =SUM(C20:C34) -> 0 | D36: =SUM(D20:D34) -> #DIV/0! | F36: =SUM(F20:F34) -> 0 | G36: =SUM(G20:G34) -> 0 | H36: =G36/F36 -> #DIV/0!

Sheet A700 Revue EAP
D1: ='A Synthèse'!D1:M2 -> 0
A3: FOURNISSEURS - ACHATS
A6: Fait par : | B6: ='A Synthèse'!B6 -> BRA | C6: Revu par : | D6: ='A Synthèse'!D6 -> 0 | E6: Revue EAP | M6: Date Clôture | O6: XRef
A7: Le : | B7: ='A Synthèse'!B7 -> 0 | C7: Le : | D7: ='A Synthèse'!D7 -> 0 | M7: ='A Synthèse'!M7:N7 -> 31/12/N | O7: A700
O8: A Synthèse
A9: Risque d'anomalies significatives | D9: ='A Synthèse'!D9:E9 -> Elevé | F9: Seuil d'investigation | J9: ='A Synthèse'!J9:K9 -> 14.7 | L9: Niveau de diligences | O9: ='A Synthèse'!O9:P9 -> PE
A11: Objectif Contrôle de l'évaluation et de la présentation des effets à payer Travail effectué Rapprocher la comptabilité du détail des effets à payer par date d’échéance - contrôle apurement des EAP si l'antériorité n'est pas satisfaisante. S’assurer que tous les effets à payer sont à échéance post clôture, dans le cas contraire proposer le reclassement
A13: Conclusion sur le contrôle
A17: Rapprochemenent Balance générale / état des EAP
A19: Montant des effets à payer en comptabilité
A21: Etat des effets à payer à la clôture
A23: écart | D23: =D19-D21 -> 0
A26: Test de détail : contrôle antériorité des EAP
B28: N° Fournisseurs | C28: Nom fournisseurs | D28: Solde | E28: Antériorité | F28: Apurement | G28: X-Réf | H28: Remarques
C44: Total Sélection Fournisseurs - Effets à payer | D44: =SUM(D29:D42) -> 0
C46: Total Fournisseurs - Effets à payer
C48: % de contrôle | D48: =+D44/D46 -> #DIV/0!
